[{"Roaster Location": "Seoul, South Korea", "Coffee Origin": "Mogiana Region, Minas Gerais State, Brazil.", "Roast Level": "Medium-Light", "Agtron": "61/80", "Est. Price": "KRW 32,000/500 grams", "Review Date": "March 2015", "Aroma": "8", "Acidity ": "8", "Body": "8", "Flavor": "9", "Aftertaste": "8"}, {"Roaster Location": "Lincoln, California", "Coffee Origin": "Boquete growing region, western Panama.", "Roast Level": "Dark", "Agtron": "36/44", "Est. Price": "$29.99/12 ounces", "Review Date": "March 2015", "Aroma": "8", "Acidity ": "8", "Body": "8", "Flavor": "8", "Aftertaste": "7"}, {"Roaster Location": "Coroico, Bolivia.", "Coffee Origin": "La Paz Department, Western Bolivia.", "Roast Level": "Medium-Light", "Agtron": "57/74", "Est. Price": "See review note", "Review Date": "February 2015", "Aroma": "9", "Acidity ": "8", "Body": "8", "Flavor": "9", "Aftertaste": "8"}, {"Roaster Location": "Sacramento, California", "Coffee Origin": "Nyamagabe region, Rwanda.", "Roast Level": "Medium-Light", "Agtron": "54/73", "Est. Price": "$19.50/12 ounces", "Review Date": "February 2015", "Aroma": "8", "Acidity ": "9", "Body": "9", "Flavor": "9", "Aftertaste": "8"}, {"Roaster Location": "Belmar, New Jersey", "Coffee Origin": "Gakui, Central Kenya.", "Roast Level": "Medium", "Agtron": "51/65", "Est. Price": "$18.50/12 ounces", "Review Date": "February 2015", "Aroma": "9", "Acidity ": "9", "Body": "8", "Flavor": "9", "Aftertaste": "8"}, {"Roaster Location": "Victoria, British Columbia, Canada", "Coffee Origin": "Antigua Valley, Guatemala.", "Roast Level": "Medium", "Agtron": "48/59", "Est. Price": "CAD $15.99/16 ounces", "Review Date": "February 2015", "Aroma": "8", "Acidity ": "8", "Body": "8", "Flavor": "8", "Aftertaste": "8"}, {"Roaster Location": "Salem, Massachusetts", "Coffee Origin": "Rusizi District, Western Rwanda.", "Roast Level": "Light", "Agtron": "65/90", "Est. Price": "$15.95/12 ounces", "Review Date": "February 2015", "Aroma": "9", "Acidity ": "9", "Body": "8", "Flavor": "9", "Aftertaste": "8"}, {"Roaster Location": "Chia-Yi, Taiwan", "Coffee Origin": "Yirgacheffe growing region, south-central Ethiopia.", "Roast Level": "Light", "Agtron": "65/88", "Est. Price": "$18.00/16 ounces", "Review Date": "February 2015", "Aroma": "9", "Acidity ": "9", "Body": "9", "Flavor": "9", "Aftertaste": "8"}, {"Roaster Location": "Chia-Yi, Taiwan", "Coffee Origin": "Yirgacheffe growing region, south-central Ethiopia.", "Roast Level": "Light", "Agtron": "62/80", "Est. Price": "$20.00/16 ounces", "Review Date": "February 2015", "Aroma": "9", "Acidity ": "9", "Body": "8", "Flavor": "9", "Aftertaste": "8"}, {"Roaster Location": "Sacramento, California", "Coffee Origin": "Nyamasheke District, Rwanda.", "Roast Level": "Medium", "Agtron": "52/66", "Est. Price": "$17.50/12 ounces", "Review Date": "February 2015", "Aroma": "9", "Acidity ": "8", "Body": "9", "Flavor": "9", "Aftertaste": "8"}, {"Roaster Location": "Boulder, Colorado", "Coffee Origin": "Meru County, central Kenya.", "Roast Level": "Medium", "Agtron": "53/68", "Est. Price": "$18.00/12 ounces", "Review Date": "February 2015", "Aroma": "9", "Acidity ": "8", "Body": "9", "Flavor": "9", "Aftertaste": "9"}, {"Roaster Location": "Seattle, Washington", "Coffee Origin": "Nyeri growing region, south-central Kenya.", "Roast Level": "Medium", "Agtron": "49/65", "Est. Price": "$19.50/12 ounces", "Review Date": "February 2015", "Aroma": "9", "Acidity ": "9", "Body": "9", "Flavor": "9", "Aftertaste": "8"}, {"Roaster Location": "Boulder, Colorado", "Coffee Origin": "Yirgacheffe growing region, southern Ethiopia.", "Roast Level": "Medium-Light", "Agtron": "58/83", "Est. Price": "$18.00/12 ounces", "Review Date": "February 2015", "Aroma": "9", "Acidity ": "9", "Body": "9", "Flavor": "8", "Aftertaste": "8"}, {"Roaster Location": "Boulder, Colorado", "Coffee Origin": "Not disclosed.", "Roast Level": "Medium", "Agtron": "50/60", "Est. Price": "$12.00/12 ounces", "Review Date": "February 2015", "Aroma": "9", "Body": "9", "Flavor": "9", "Aftertaste": "7", "With Milk": "9"}, {"Roaster Location": "Torrington, Connecticut", "Coffee Origin": "Konga District, Yirgacheffe growing region, southern Ethiopia.", "Roast Level": "Very Dark", "Agtron": "0/58", "Est. Price": "$9.99/10 capsules", "Review Date": "February 2015", "Aroma": "9", "Acidity ": "7", "Body": "8", "Flavor": "8", "Aftertaste": "8"}, {"Roaster Location": "New York, New York", "Coffee Origin": "El Salvador.", "Roast Level": "Very Dark", "Agtron": "0/49", "Est. Price": "$6.99/12 capsules", "Review Date": "February 2015", "Aroma": "7", "Acidity ": "8", "Body": "8", "Flavor": "8", "Aftertaste": "7"}, {"Roaster Location": "Lausanne, Switzerland", "Coffee Origin": "Colombia; Brazil.", "Roast Level": "Very Dark", "Agtron": "0/58", "Est. Price": "$11.00/10 capsules", "Review Date": "February 2015", "Aroma": "8", "Acidity ": "7", "Body": "8", "Flavor": "8", "Aftertaste": "7"}, {"Roaster Location": "Taipei City, Taiwan", "Coffee Origin": "Central Taiwan.", "Roast Level": "Medium-Dark", "Agtron": "0/86", "Est. Price": "NA", "Review Date": "February 2015", "Aroma": "8", "Acidity ": "7", "Body": "8", "Flavor": "8", "Aftertaste": "7"}, {"Roaster Location": "Waterbury, Vermont", "Coffee Origin": "Northern Sumatra, Indonesia.", "Roast Level": "Very Dark", "Agtron": "0/39", "Est. Price": "$17.99/24 K-cups", "Review Date": "February 2015", "Aroma": "8", "Acidity ": "7", "Body": "8", "Flavor": "8", "Aftertaste": "7"}, {"Roaster Location": "Heredia, Costa Rica", "Coffee Origin": "Tarrazu growing region, Costa Rica.", "Roast Level": "Very Dark", "Agtron": "0/48", "Est. Price": "$13.95/18 capsules", "Review Date": "February 2015", "Aroma": "8", "Acidity ": "7", "Body": "7", "Flavor": "8", "Aftertaste": "7"}, {"Roaster Location": "Clinton, Washington", "Coffee Origin": "Not disclosed.", "Roast Level": "Very Dark", "Agtron": "0/34", "Est. Price": "$9.99/12 capsules", "Review Date": "February 2015", "Aroma": "8", "Acidity ": "7", "Body": "8", "Flavor": "8", "Aftertaste": "6"}, {"Roaster Location": "Clark, Wyoming", "Coffee Origin": "Sidama (also Sidamo) growing region, southern Ethiopia.", "Roast Level": "Dark", "Agtron": "0/78", "Est. Price": "$11.99/10 capsules", "Review Date": "February 2015", "Aroma": "8", "Acidity ": "7", "Body": "7", "Flavor": "8", "Aftertaste": "7"}, {"Roaster Location": "Seattle, Washington", "Coffee Origin": "Africa; Central and South America.", "Roast Level": "Very Dark", "Agtron": "0/65", "Est. Price": "$24.95/32 K-Cups", "Review Date": "February 2015", "Aroma": "8", "Acidity ": "6", "Body": "8", "Flavor": "8", "Aftertaste": "7"}, {"Roaster Location": "Emeryville, California", "Coffee Origin": "Huila Department, southwestern Colombia; southern Ethiopia.", "Roast Level": "Very Dark", "Agtron": "0/55", "Est. Price": "$13.99/16 K-Cups", "Review Date": "February 2015", "Aroma": "7", "Acidity ": "7", "Body": "8", "Flavor": "8", "Aftertaste": "7"}, {"Roaster Location": "Charlotte, North Carolina", "Coffee Origin": "Konga District, Yirgacheffe growing region, southern Ethiopia.", "Roast Level": "Medium-Light", "Agtron": "60/78", "Est. Price": "$12.99/12 ounces", "Review Date": "January 2015", "Aroma": "9", "Acidity ": "8", "Body": "8", "Flavor": "9", "Aftertaste": "8"}, {"Roaster Location": "Taichung City, Taiwan", "Coffee Origin": "Not disclosed.", "Roast Level": "Medium-Dark", "Agtron": "46/50", "Est. Price": "$20.00/16 ounces", "Review Date": "January 2015", "Aroma": "8", "Body": "8", "Flavor": "9", "Aftertaste": "8", "With Milk": "9"}, {"Roaster Location": "Chicago, Illinois", "Coffee Origin": "Eastern slopes of Volcan Baru, western Panama.", "Roast Level": "Medium-Light", "Agtron": "52/75", "Est. Price": "$17.50/12 ounces", "Review Date": "January 2015", "Aroma": "8", "Acidity ": "8", "Body": "9", "Flavor": "9", "Aftertaste": "8"}, {"Roaster Location": "Taichung City, Taiwan", "Coffee Origin": "Not disclosed.", "Roast Level": "Medium-Dark", "Agtron": "43/52", "Est. Price": "$20.00/16 ounces", "Review Date": "January 2015", "Aroma": "8", "Body": "8", "Flavor": "9", "Aftertaste": "8", "With Milk": "9"}, {"Roaster Location": "Chicago, Illinois", "Coffee Origin": "Thika growing region, central Kenya.", "Roast Level": "Medium-Light", "Agtron": "60/76", "Est. Price": "$17.50/12 ounces", "Review Date": "January 2015", "Aroma": "8", "Acidity ": "8", "Body": "8", "Flavor": "9", "Aftertaste": "8"}, {"Roaster Location": "Vancouver, British Columbia, Canada", "Coffee Origin": "Brazil; Guatemala; Costa Rica.", "Roast Level": "Medium-Dark", "Agtron": "43/56", "Est. Price": "$14.99/12 ounces", "Review Date": "January 2015", "Aroma": "9", "Body": "9", "Flavor": "8", "Aftertaste": "7", "With Milk": "8"}, {"Roaster Location": "New Taipei City, Taiwan", "Coffee Origin": "Central Kenya.", "Roast Level": "Medium-Light", "Agtron": "56/79", "Est. Price": "NT$500/8 ounces", "Review Date": "January 2015", "Aroma": "9", "Acidity ": "9", "Body": "9", "Flavor": "9", "Aftertaste": "9"}, {"Roaster Location": "Ramsey, Minnesota", "Coffee Origin": "Guji Zone, Oromia Region, Sidamo growing region, south-central Ethiopia.", "Roast Level": "Medium", "Agtron": "52/65", "Est. Price": "$14.95/12 ounces", "Review Date": "January 2015", "Aroma": "9", "Acidity ": "9", "Body": "9", "Flavor": "9", "Aftertaste": "9"}, {"Roaster Location": "New Taipei City, Taiwan", "Coffee Origin": "Ethiopia; Sumatra; Central America.", "Roast Level": "Medium", "Agtron": "48/54", "Est. Price": "NT$290/8 ounces", "Review Date": "January 2015", "Aroma": "9", "Body": "9", "Flavor": "9", "Aftertaste": "8", "With Milk": "9"}, {"Roaster Location": "Ramsey, Minnesota", "Coffee Origin": "Los Robles de Naranjo, West Valley growing region, Costa Rica.", "Roast Level": "Medium", "Agtron": "49/57", "Est. Price": "$14.95/12 ounces", "Review Date": "January 2015", "Aroma": "8", "Body": "9", "Flavor": "9", "Aftertaste": "8", "With Milk": "9"}, {"Roaster Location": "New Taipei City, Taiwan", "Coffee Origin": "Aceh growing region, northwestern Sumatra, Indonesia.", "Roast Level": "Medium-Dark", "Agtron": "45/49", "Est. Price": "NT$350/8 ounces", "Review Date": "January 2015", "Aroma": "9", "Acidity ": "7", "Body": "8", "Flavor": "9", "Aftertaste": "8"}, {"Roaster Location": "La Jolla, California", "Coffee Origin": "Cañas Verdes, Boquete growing region, western Panama.", "Roast Level": "Light", "Agtron": "71/89", "Est. Price": "$45.00/8 ounces", "Review Date": "January 2015", "Aroma": "10", "Acidity ": "9", "Body": "9", "Flavor": "10", "Aftertaste": "8"}, {"Roaster Location": "Bangkok, Thailand", "Coffee Origin": "Chiang Rai Province, northern Thailand.", "Roast Level": "Medium-Dark", "Agtron": "45/53", "Est. Price": "THB $200/250 grams", "Review Date": "January 2015", "Aroma": "9", "Body": "8", "Flavor": "9", "Aftertaste": "8", "With Milk": "8"}, {"Roaster Location": "Bangkok, Thailand", "Coffee Origin": "Chiang Rai Province, northern Thailand.", "Roast Level": "Medium", "Agtron": "47/62", "Est. Price": "THB $200/250 grams", "Review Date": "January 2015", "Aroma": "9", "Body": "8", "Flavor": "9", "Aftertaste": "7", "With Milk": "8"}, {"Roaster Location": "Bangkok, Thailand", "Coffee Origin": "Chiang Rai Province, northern Thailand.", "Roast Level": "Light", "Agtron": "66/97", "Est. Price": "THB $200/250 grams", "Review Date": "January 2015", "Aroma": "8", "Acidity ": "8", "Body": "8", "Flavor": "9", "Aftertaste": "7"}, {"Roaster Location": "San Diego, California", "Coffee Origin": "Sidamo (also Sidama) growing region, southern Ethiopia.", "Roast Level": "Medium", "Agtron": "53/66", "Est. Price": "$17.00/12 ounces", "Review Date": "December 2014", "Aroma": "9", "Acidity ": "8", "Body": "9", "Flavor": "9", "Aftertaste": "9"}, {"Roaster Location": "Bedford, New Hampshire", "Coffee Origin": "South-central Kenya.", "Roast Level": "Medium-Light", "Agtron": "57/80", "Est. Price": "$15.00/12 ounces", "Review Date": "December 2014", "Aroma": "9", "Acidity ": "9", "Body": "8", "Flavor": "9", "Aftertaste": "8"}, {"Roaster Location": "Seattle, Washington", "Coffee Origin": "Santa Barbara Department, Honduras.", "Roast Level": "Medium-Light", "Agtron": "58/66", "Est. Price": "$17.25/12 ounces", "Review Date": "December 2014", "Aroma": "8", "Acidity ": "8", "Body": "9", "Flavor": "9", "Aftertaste": "8"}, {"Roaster Location": "Newbury Park, California", "Coffee Origin": "Acatenango growing region, Guatemala.", "Roast Level": "Medium-Light", "Agtron": "58/74", "Est. Price": "$20.00/6 ounces", "Review Date": "December 2014", "Aroma": "8", "Acidity ": "9", "Body": "9", "Flavor": "9", "Aftertaste": "8"}, {"Roaster Location": "Newbury Park, California", "Coffee Origin": "Konga District, Yirgacheffe growing region, southern Ethiopia.", "Roast Level": "Medium-Light", "Agtron": "54/72", "Est. Price": "$19.00/12 ounces", "Review Date": "December 2014", "Aroma": "9", "Acidity ": "8", "Body": "8", "Flavor": "9", "Aftertaste": "8"}, {"Roaster Location": "Los Angeles, California", "Coffee Origin": "Yirgacheffe growing district, southern Ethiopia.", "Roast Level": "Light", "Agtron": "64/85", "Est. Price": "$25.00/12 ounces", "Review Date": "December 2014", "Aroma": "9", "Acidity ": "9", "Body": "9", "Flavor": "10", "Aftertaste": "8"}, {"Roaster Location": "Holualoa, Hawaii", "Coffee Origin": "Holualoa, North Kona growing district, “Big Island” of Hawaii.", "Roast Level": "Medium", "Agtron": "53/68", "Est. Price": "$35.95/8 ounces", "Review Date": "December 2014", "Aroma": "9", "Acidity ": "9", "Body": "9", "Flavor": "9", "Aftertaste": "8"}, {"Roaster Location": "New York, New York", "Coffee Origin": "Yirgacheffe growing region, southern Ethiopia.", "Roast Level": "Medium-Light", "Agtron": "57/74", "Est. Price": "$9.99/16 ounces", "Review Date": "December 2014", "Aroma": "9", "Acidity ": "8", "Body": "8", "Flavor": "9", "Aftertaste": "8"}, {"Roaster Location": "Kansas City, Missouri", "Coffee Origin": "Nyeri growing region, south-central Kenya.", "Roast Level": "Medium-Light", "Agtron": "59/74", "Est. Price": "$17.25/12 ounces", "Review Date": "December 2014", "Aroma": "8", "Acidity ": "9", "Body": "8", "Flavor": "9", "Aftertaste": "8"}, {"Roaster Location": "Kansas City, Missouri", "Coffee Origin": "Not disclosed.", "Roast Level": "Medium-Light", "Agtron": "58/71", "Est. Price": "$15.00/12 ounces", "Review Date": "December 2014", "Aroma": "8", "Body": "9", "Flavor": "8", "Aftertaste": "8", "With Milk": "8"}, {"Roaster Location": "Driftless, Wisconsin", "Coffee Origin": "Embu County, Kenya.", "Roast Level": "Medium-Light", "Agtron": "58/81", "Est. Price": "$18.50/12 ounces", "Review Date": "December 2014", "Aroma": "9", "Acidity ": "9", "Body": "8", "Flavor": "9", "Aftertaste": "8"}, {"Roaster Location": "Driftless, Wisconsin", "Coffee Origin": "Valle del Cauca growing region, Colombia.", "Roast Level": "Medium-Light", "Agtron": "60/74", "Est. Price": "$15.75/12 ounces", "Review Date": "December 2014", "Aroma": "9", "Acidity ": "8", "Body": "8", "Flavor": "8", "Aftertaste": "8"}, {"Roaster Location": "Lee, Massachusetts", "Coffee Origin": "Southern and/or western Ethiopia.", "Roast Level": "Light", "Agtron": "66/84", "Est. Price": "NA", "Review Date": "December 2014", "Aroma": "10", "Acidity ": "9", "Body": "9", "Flavor": "9", "Aftertaste": "8"}, {"Roaster Location": "Chia-Yi, Taiwan", "Coffee Origin": "Nyeri County, Central Kenya.", "Roast Level": "Medium", "Agtron": "49/66", "Est. Price": "$20.00/16 ounces", "Review Date": "December 2014", "Aroma": "9", "Acidity ": "9", "Body": "9", "Flavor": "9", "Aftertaste": "9"}, {"Roaster Location": "Taoyuan, Taiwan", "Coffee Origin": "Northern Thailand.", "Roast Level": "Medium-Light", "Agtron": "60/78", "Est. Price": "TWD $500/8 ounces", "Review Date": "December 2014", "Aroma": "8", "Acidity ": "9", "Body": "8", "Flavor": "9", "Aftertaste": "8"}, {"Roaster Location": "Topeka, Kansas", "Coffee Origin": "Boquete growing region, western Panama.", "Roast Level": "Light", "Agtron": "62/88", "Est. Price": "$40.00/8 ounces", "Review Date": "December 2014", "Aroma": "9", "Acidity ": "9", "Body": "9", "Flavor": "9", "Aftertaste": "9"}, {"Roaster Location": "Olympia, Washington", "Coffee Origin": "El Salvador; Kenya.", "Roast Level": "Medium-Light", "Agtron": "59/78", "Est. Price": "$17.25/12 ounces", "Review Date": "December 2014", "Aroma": "9", "Acidity ": "9", "Body": "9", "Flavor": "9", "Aftertaste": "9"}, {"Roaster Location": "Sacramento, California", "Coffee Origin": "Gedeo zone, Yirgacheffe growing region, south-central Ethiopia.", "Roast Level": "Medium-Light", "Agtron": "55/73", "Est. Price": "$18.00/12 ounces", "Review Date": "December 2014", "Aroma": "9", "Acidity ": "9", "Body": "9", "Flavor": "9", "Aftertaste": "9"}, {"Roaster Location": "Los Angeles, California", "Coffee Origin": "Boquete growing region, western Panama.", "Roast Level": "Light", "Agtron": "67/88", "Est. Price": "$24.00/150 grams", "Review Date": "December 2014", "Aroma": "9", "Acidity ": "9", "Body": "9", "Flavor": "10", "Aftertaste": "8"}, {"Roaster Location": "Sacramento, California", "Coffee Origin": "Boquete growing region, western Panama", "Roast Level": "Medium", "Agtron": "50/65", "Est. Price": "$62.00/8 ounces", "Review Date": "December 2014", "Aroma": "9", "Acidity ": "8", "Body": "8", "Flavor": "10", "Aftertaste": "9"}, {"Roaster Location": "Longwood, Florida", "Coffee Origin": "Central America.", "Roast Level": "Medium", "Agtron": "46/64", "Est. Price": "$12.50/12 ounces", "Review Date": "December 2014", "Aroma": "9", "Acidity ": "9", "Body": "9", "Flavor": "9", "Aftertaste": "8"}, {"Roaster Location": "Boulder, Colorado", "Coffee Origin": "San Fernando, Nueva Segovia region, Nicaragua.", "Roast Level": "Medium-Light", "Agtron": "57/73", "Est. Price": "$18.00/12 ounces", "Review Date": "December 2014", "Aroma": "9", "Acidity ": "8", "Body": "9", "Flavor": "9", "Aftertaste": "9"}, {"Roaster Location": "Bellingham, Washington", "Coffee Origin": "South-central Kenya.", "Roast Level": "Medium", "Agtron": "49/64", "Est. Price": "$16.00/150 grams", "Review Date": "December 2014", "Aroma": "9", "Acidity ": "9", "Body": "8", "Flavor": "9", "Aftertaste": "9"}, {"Roaster Location": "Bedford, New Hampshire", "Coffee Origin": "Kenya; Papua New Guinea.", "Roast Level": "Medium-Light", "Agtron": "59/80", "Est. Price": "$14.50/12 ounces", "Review Date": "December 2014", "Aroma": "9", "Acidity ": "9", "Body": "9", "Flavor": "9", "Aftertaste": "7"}, {"Roaster Location": "Seattle, Washington", "Coffee Origin": "Kenya; Panama; Ethiopia.", "Roast Level": "Light", "Agtron": "61/83", "Est. Price": "$14.45/12 ounces", "Review Date": "December 2014", "Aroma": "9", "Acidity ": "9", "Body": "8", "Flavor": "9", "Aftertaste": "8"}, {"Roaster Location": "Everett, Washington", "Coffee Origin": "Kenya; Guatemala.", "Roast Level": "Medium", "Agtron": "54/67", "Est. Price": "$17.50/16 ounces", "Review Date": "December 2014", "Aroma": "8", "Acidity ": "8", "Body": "9", "Flavor": "9", "Aftertaste": "9"}, {"Roaster Location": "Goleta, California", "Coffee Origin": "California, USA.", "Roast Level": "Light", "Agtron": "65/80", "Est. Price": "$27.00/5 ounces", "Review Date": "December 2014", "Aroma": "9", "Acidity ": "8", "Body": "8", "Flavor": "8", "Aftertaste": "8"}, {"Roaster Location": "Sacramento, California", "Coffee Origin": "Nyeri County, Central Highlands, Kenya.", "Roast Level": "Medium-Light", "Agtron": "54/78", "Est. Price": "$16.75/12 ounces", "Review Date": "December 2014", "Aroma": "9", "Acidity ": "9", "Body": "8", "Flavor": "9", "Aftertaste": "8"}, {"Roaster Location": "Taichung, Taiwan", "Coffee Origin": "Guatemala; Brazil.", "Roast Level": "Medium", "Agtron": "54/63", "Est. Price": "TWD $600 / 225 grams", "Review Date": "December 2014", "Aroma": "8", "Acidity ": "8", "Body": "8", "Flavor": "9", "Aftertaste": "9"}, {"Roaster Location": "Taichung, Taiwan", "Coffee Origin": "Guatemala; Brazil.", "Roast Level": "Medium-Dark", "Agtron": "43/54", "Est. Price": "TWD $400 / 225 grams", "Review Date": "December 2014", "Aroma": "8", "Body": "8", "Flavor": "9", "Aftertaste": "8", "With Milk": "8"}, {"Roaster Location": "Jackson, Mississippi", "Coffee Origin": "Huehuetenango growing region, Guatemala.", "Roast Level": "Medium-Light", "Agtron": "52/75", "Est. Price": "$14.00/12 ounces", "Review Date": "December 2014", "Aroma": "8", "Acidity ": "8", "Body": "8", "Flavor": "8", "Aftertaste": "8"}, {"Roaster Location": "Taichung, Taiwan", "Coffee Origin": "Ethiopia; Guatemala; Brazil; Colombia; Rwanda.", "Roast Level": "Medium", "Agtron": "55/63", "Est. Price": "TWD $500 / 225 grams", "Review Date": "December 2014", "Aroma": "8", "Acidity ": "8", "Body": "8", "Flavor": "8", "Aftertaste": "8"}, {"Roaster Location": "Yorktown Heights, New York", "Coffee Origin": "Yirgacheffe growing region, southern Ethiopia.", "Roast Level": "Medium", "Agtron": "51/67", "Est. Price": "$30.00/12 ounces", "Review Date": "December 2014", "Aroma": "10", "Acidity ": "8", "Body": "9", "Flavor": "9", "Aftertaste": "9"}, {"Roaster Location": "Lee, Massachusetts", "Coffee Origin": "Silla Del Pando, Volcan, Panama.", "Roast Level": "Light", "Agtron": "74/101", "Est. Price": "$72.45/12 ounces", "Review Date": "December 2014", "Aroma": "9", "Acidity ": "9", "Body": "9", "Flavor": "9", "Aftertaste": "9"}, {"Roaster Location": "Berkeley, California", "Coffee Origin": "Nyeri County, Central Highlands, Kenya.", "Roast Level": "Medium", "Agtron": "54/66", "Est. Price": "$12.99/12 ounces", "Review Date": "December 2014", "Aroma": "9", "Acidity ": "9", "Body": "8", "Flavor": "9", "Aftertaste": "9"}, {"Roaster Location": "Lee, Massachusetts", "Coffee Origin": "Sidamo (also Sidama) growing region, southern Ethiopia.", "Roast Level": "Light", "Agtron": "64/89", "Est. Price": "$30.95/12 ounces", "Review Date": "December 2014", "Aroma": "9", "Acidity ": "9", "Body": "8", "Flavor": "9", "Aftertaste": "9"}, {"Roaster Location": "Berkeley, California", "Coffee Origin": "Tarrazu growing region, central Costa Rica.", "Roast Level": "Medium-Light", "Agtron": "55/67", "Est. Price": "$12.99/12 ounces", "Review Date": "December 2014", "Aroma": "9", "Acidity ": "8", "Body": "9", "Flavor": "9", "Aftertaste": "8"}, {"Roaster Location": "Lee, Massachusetts", "Coffee Origin": "Silla Del Pando, Volcan, Panama.", "Roast Level": "Light", "Agtron": "66/93", "Est. Price": "$47.45/12 ounces", "Review Date": "December 2014", "Aroma": "9", "Acidity ": "9", "Body": "8", "Flavor": "9", "Aftertaste": "8"}, {"Roaster Location": "Berkeley, California", "Coffee Origin": "Toraja growing region, south-central Sulawesi, Indonesia.", "Roast Level": "Medium", "Agtron": "50/63", "Est. Price": "$12.99/12 ounces", "Review Date": "December 2014", "Aroma": "9", "Acidity ": "8", "Body": "8", "Flavor": "8", "Aftertaste": "7"}, {"Roaster Location": "Berkeley, California", "Coffee Origin": "Eastern Java, Indonesia.", "Roast Level": "Medium", "Agtron": "49/58", "Est. Price": "$12.99/12 ounces", "Review Date": "December 2014", "Aroma": "8", "Acidity ": "7", "Body": "8", "Flavor": "8", "Aftertaste": "7"}, {"Roaster Location": "Chia-Yi, Taiwan", "Coffee Origin": "Central Valley growing region, Costa Rica.", "Roast Level": "Medium-Light", "Agtron": "56/76", "Est. Price": "$16.00/16 ounces", "Review Date": "November 2014", "Aroma": "9", "Acidity ": "8", "Body": "9", "Flavor": "9", "Aftertaste": "7"}, {"Roaster Location": "Pu’Er, Yunnan Province, China", "Coffee Origin": "Yunnan Province, China.", "Roast Level": "Medium-Light", "Agtron": "55/86", "Est. Price": "RMB $60/125 grams", "Review Date": "November 2014", "Aroma": "7", "Acidity ": "8", "Body": "8", "Flavor": "8", "Aftertaste": "7"}, {"Roaster Location": "Billings, Montana.", "Coffee Origin": "South America; Africa.", "Roast Level": "Medium", "Agtron": "53/66", "Est. Price": "$12.75/12 ounces", "Review Date": "November 2014", "Aroma": "9", "Body": "8", "Flavor": "9", "Aftertaste": "8", "With Milk": "9"}, {"Roaster Location": "Billings, Montana.", "Coffee Origin": "Murang’a County, central Kenya.", "Roast Level": "Light", "Agtron": "63/85", "Est. Price": "$14.50/12 ounces", "Review Date": "November 2014", "Aroma": "9", "Acidity ": "9", "Body": "8", "Flavor": "9", "Aftertaste": "8"}, {"Roaster Location": "Ramsey, Minnesota", "Coffee Origin": "Kochere, Yirgacheffe growing region, south-central Ethiopia.", "Roast Level": "Medium", "Agtron": "52/69", "Est. Price": "$16.95/12 ounces", "Review Date": "November 2014", "Aroma": "10", "Acidity ": "8", "Body": "9", "Flavor": "9", "Aftertaste": "8"}, {"Roaster Location": "Madison, Wisconsin", "Coffee Origin": "Northern Sumatra, Indonesia.", "Roast Level": "Medium-Light", "Agtron": "54/78", "Est. Price": "$18.50/12 ounces", "Review Date": "November 2014", "Aroma": "9", "Acidity ": "9", "Body": "9", "Flavor": "9", "Aftertaste": "9"}, {"Roaster Location": "Ramsey, Minnesota", "Coffee Origin": "Not disclosed.", "Roast Level": "Medium-Dark", "Agtron": "41/51", "Est. Price": "$12.95/12 ounces", "Review Date": "November 2014", "Aroma": "9", "Body": "9", "Flavor": "9", "Aftertaste": "8", "With Milk": "8"}, {"Roaster Location": "Madison, Wisconsin", "Coffee Origin": "Pitalito, Huila Department, southwestern Colombia.", "Roast Level": "Light", "Agtron": "63/80", "Est. Price": "$14.25/12 ounces", "Review Date": "November 2014", "Aroma": "9", "Acidity ": "8", "Body": "8", "Flavor": "8", "Aftertaste": "8"}, {"Roaster Location": "Lexington, Virginia", "Coffee Origin": "Konga District, Yirgacheffe growing region, southern Ethiopia.", "Roast Level": "Medium-Light", "Agtron": "56/76", "Est. Price": "$16.95/12 ounces", "Review Date": "November 2014", "Aroma": "9", "Acidity ": "9", "Body": "8", "Flavor": "9", "Aftertaste": "9"}, {"Roaster Location": "Lexington, Virginia", "Coffee Origin": "Nyeri County, Central Highlands, Kenya.", "Roast Level": "Medium-Light", "Agtron": "51/77", "Est. Price": "$17.50/12 ounces", "Review Date": "November 2014", "Aroma": "9", "Acidity ": "8", "Body": "8", "Flavor": "9", "Aftertaste": "9"}, {"Roaster Location": "Lexington, Virginia", "Coffee Origin": "Wahgi Valley, Western Highlands, Papua New Guinea.", "Roast Level": "Medium-Light", "Agtron": "53/73", "Est. Price": "$13.95/12 ounces", "Review Date": "November 2014", "Aroma": "8", "Acidity ": "8", "Body": "9", "Flavor": "9", "Aftertaste": "8"}, {"Roaster Location": "Lexington, Virginia", "Coffee Origin": "Valle de Cauca Department, southwestern Colombia.", "Roast Level": "Medium-Light", "Agtron": "59/80", "Est. Price": "$14.95/12 ounces", "Review Date": "November 2014", "Aroma": "8", "Acidity ": "8", "Body": "8", "Flavor": "9", "Aftertaste": "8"}, {"Roaster Location": "Taoyuan City, Taiwan", "Coffee Origin": "Central Kenya.", "Roast Level": "Medium", "Agtron": "47/62", "Est. Price": "NTD$ 1600 / 16 ounces", "Review Date": "November 2014", "Aroma": "9", "Body": "9", "Flavor": "10", "Aftertaste": "8", "With Milk": "9"}, {"Roaster Location": "Kaohsiung City, Taiwan", "Coffee Origin": "Yirgacheffe growing region, southern Ethiopia.", "Roast Level": "Medium", "Agtron": "52/68", "Est. Price": "NTD $1000/16 ounces", "Review Date": "November 2014", "Aroma": "9", "Acidity ": "9", "Body": "9", "Flavor": "9", "Aftertaste": "8"}, {"Roaster Location": "Taichung City, Taiwan", "Coffee Origin": "Sidamo (also Sidama) growing region, southern Ethiopia.", "Roast Level": "Medium-Light", "Agtron": "59/77", "Est. Price": "$450 NTD/100 grams", "Review Date": "November 2014", "Aroma": "9", "Acidity ": "9", "Body": "8", "Flavor": "9", "Aftertaste": "8"}, {"Roaster Location": "Kaohsiung City, Taiwan", "Coffee Origin": "Central Kenya.", "Roast Level": "Medium", "Agtron": "49/60", "Est. Price": "NTD $1800/16 ounces", "Review Date": "November 2014", "Aroma": "9", "Acidity ": "7", "Body": "8", "Flavor": "9", "Aftertaste": "8"}, {"Roaster Location": "Taichung City, Taiwan", "Coffee Origin": "Konga District, Yirgacheffe growing region, southern Ethiopia.", "Roast Level": "Medium", "Agtron": "54/67", "Est. Price": "$450 NTD/100 grams", "Review Date": "November 2014", "Aroma": "9", "Acidity ": "7", "Body": "9", "Flavor": "9", "Aftertaste": "7"}, {"Roaster Location": "Jackson, MIssissippi", "Coffee Origin": "San Marcos, Tarrazu growing region, central Costa Rica.", "Roast Level": "Medium-Light", "Agtron": "55/80", "Est. Price": "$14.00/12 ounces", "Review Date": "November 2014", "Aroma": "8", "Acidity ": "8", "Body": "8", "Flavor": "8", "Aftertaste": "8"}, {"Roaster Location": "Longwood, Florida", "Coffee Origin": "Boquete growing region, western Panama.", "Roast Level": "Medium", "Agtron": "42/63", "Est. Price": "$33.95/12 ounces", "Review Date": "November 2014", "Aroma": "9", "Acidity ": "9", "Body": "9", "Flavor": "9", "Aftertaste": "9"}, {"Roaster Location": "Holualoa, Hawaii", "Coffee Origin": "Holualoa, North Kona growing district, “Big Island” of Hawaii.", "Roast Level": "Medium-Light", "Agtron": "61/77", "Est. Price": "$34.95/8 ounces", "Review Date": "November 2014", "Aroma": "9", "Acidity ": "9", "Body": "9", "Flavor": "9", "Aftertaste": "9"}, {"Roaster Location": "Sacramento, California", "Coffee Origin": "San Fernando, Nueva Segovia region, Nicaragua.", "Roast Level": "Medium-Light", "Agtron": "56/73", "Est. Price": "$18.00/12 ounces", "Review Date": "November 2014", "Aroma": "9", "Acidity ": "8", "Body": "9", "Flavor": "9", "Aftertaste": "9"}, {"Roaster Location": "Sacramento, California", "Coffee Origin": "El Salto, Boquete growing region, Panama.", "Roast Level": "Light", "Agtron": "61/81", "Est. Price": "$47.00/8 ounces", "Review Date": "November 2014", "Aroma": "9", "Acidity ": "9", "Body": "8", "Flavor": "9", "Aftertaste": "9"}, {"Roaster Location": "Billings, Montana.", "Coffee Origin": "Acatenango growing region, Guatemala.", "Roast Level": "Light", "Agtron": "72/87", "Est. Price": "$22.00/8 ounces", "Review Date": "November 2014", "Aroma": "9", "Acidity ": "8", "Body": "9", "Flavor": "9", "Aftertaste": "9"}, {"Roaster Location": "Topeka, Kansas", "Coffee Origin": "Palencia, central Guatemala.", "Roast Level": "Medium-Light", "Agtron": "60/78", "Est. Price": "$22.78/12 ounces", "Review Date": "November 2014", "Aroma": "9", "Acidity ": "8", "Body": "8", "Flavor": "9", "Aftertaste": "8"}, {"Roaster Location": "Boulder, Colorado", "Coffee Origin": "Cañas Verdes, Boquete growing region, western Panama.", "Roast Level": "Medium-Light", "Agtron": "55/75", "Est. Price": "$48.50/8 ounces", "Review Date": "November 2014", "Aroma": "9", "Acidity ": "8", "Body": "9", "Flavor": "9", "Aftertaste": "8"}, {"Roaster Location": "San Rafael, California", "Coffee Origin": "Valle del Cauca growing region, Colombia.", "Roast Level": "Light", "Agtron": "60/82", "Est. Price": "$17.95/12 ounces", "Review Date": "November 2014", "Aroma": "9", "Acidity ": "9", "Body": "8", "Flavor": "9", "Aftertaste": "8"}, {"Roaster Location": "Yorktown Heights, New York", "Coffee Origin": "Murang’a County, Central Kenya.", "Roast Level": "Medium-Light", "Agtron": "51/73", "Est. Price": "$18.00/12 ounces", "Review Date": "November 2014", "Aroma": "9", "Acidity ": "8", "Body": "8", "Flavor": "9", "Aftertaste": "8"}, {"Roaster Location": "Torrington, Connecticut", "Coffee Origin": "Nueva Segovia growing region, Nicaragua.", "Roast Level": "Medium-Light", "Agtron": "59/79", "Est. Price": "$13.99/12 ounces", "Review Date": "November 2014", "Aroma": "9", "Acidity ": "8", "Body": "8", "Flavor": "9", "Aftertaste": "8"}, {"Roaster Location": "Minneapolis, Minnesota", "Coffee Origin": "Saraguru growing region, southern Ecuador.", "Roast Level": "Medium-Light", "Agtron": "52/72", "Est. Price": "$22.00/12 ounces", "Review Date": "November 2014", "Aroma": "8", "Acidity ": "8", "Body": "8", "Flavor": "9", "Aftertaste": "8"}, {"Roaster Location": "Minneapolis, Minnesota", "Coffee Origin": "Indonesia; Central America.", "Roast Level": "Medium-Dark", "Agtron": "39/44", "Est. Price": "$15.99/16 ounces", "Review Date": "November 2014", "Aroma": "8", "Body": "8", "Flavor": "8", "Aftertaste": "7"}, {"Roaster Location": "Los Angeles, California", "Coffee Origin": "Nyeri County, central Kenya.", "Roast Level": "Medium-Light", "Agtron": "53/70", "Est. Price": "$19.95/12 ounces", "Review Date": "October 2014", "Aroma": "9", "Acidity ": "9", "Body": "9", "Flavor": "9", "Aftertaste": "8"}, {"Roaster Location": "Madison, Wisconsin", "Coffee Origin": "Lintong growing region, northern Sumatra, Indonesia.", "Roast Level": "Medium-Light", "Agtron": "57/71", "Est. Price": "$14.25/12 ounces", "Review Date": "October 2014", "Aroma": "8", "Acidity ": "8", "Body": "9", "Flavor": "9", "Aftertaste": "8"}, {"Roaster Location": "Taoyuan, Taiwan", "Coffee Origin": "Northern Thailand.", "Roast Level": "Medium-Light", "Agtron": "62/76", "Est. Price": "US $15.00/8 ounces", "Review Date": "October 2014", "Aroma": "8", "Acidity ": "8", "Body": "8", "Flavor": "8", "Aftertaste": "8"}, {"Roaster Location": "Port Chester, New York", "Coffee Origin": "Chichontepec growing region, El Salvador.", "Roast Level": "Medium-Light", "Agtron": "56/70", "Est. Price": "$14.36/12 ounces", "Review Date": "October 2014", "Aroma": "8", "Acidity ": "8", "Body": "8", "Flavor": "9", "Aftertaste": "8"}, {"Roaster Location": "Bedford, New Hampshire", "Coffee Origin": "Rulindo District, northern Rwanda.", "Roast Level": "Medium", "Agtron": "50/58", "Est. Price": "$14.50/12 ounces", "Review Date": "October 2014", "Aroma": "9", "Acidity ": "8", "Body": "8", "Flavor": "9", "Aftertaste": "8"}, {"Roaster Location": "Oakland, California", "Coffee Origin": "Aleta Wondo, Sidama (also Sidamo) growing region, southern Ethiopia.", "Roast Level": "Medium-Light", "Agtron": "62/75", "Est. Price": "NA", "Review Date": "October 2014", "Aroma": "9", "Acidity ": "9", "Body": "9", "Flavor": "9", "Aftertaste": "9"}, {"Roaster Location": "Oakland, California", "Coffee Origin": "Valle del Cauca growing region, Colombia.", "Roast Level": "Medium-Light", "Agtron": "53/76", "Est. Price": "NA", "Review Date": "October 2014", "Aroma": "10", "Acidity ": "9", "Body": "9", "Flavor": "9", "Aftertaste": "8"}, {"Roaster Location": "Thornton, Colorado", "Coffee Origin": "Aleta Wondo, Sidama (also Sidamo) growing region, southern Ethiopia.", "Roast Level": "Medium-Light", "Agtron": "59/79", "Est. Price": "NA", "Review Date": "October 2014", "Aroma": "9", "Acidity ": "9", "Body": "8", "Flavor": "9", "Aftertaste": "8"}, {"Roaster Location": "San Rafael, California", "Coffee Origin": "Antigua growing region, south-central Guatemala.", "Roast Level": "Medium-Light", "Agtron": "56/73", "Est. Price": "$14.95/12 ounces", "Review Date": "October 2014", "Aroma": "9", "Acidity ": "8", "Body": "8", "Flavor": "9", "Aftertaste": "8"}, {"Roaster Location": "Ithaca, New York", "Coffee Origin": "Sidama (also Sidamo) growing region, southern Ethiopia.", "Roast Level": "Medium-Light", "Agtron": "60/80", "Est. Price": "NA", "Review Date": "October 2014", "Aroma": "9", "Acidity ": "7", "Body": "8", "Flavor": "9", "Aftertaste": "8"}, {"Roaster Location": "Portland, Oregon", "Coffee Origin": "Gikongoro, Nyamagabe region, southern Rwanda.", "Roast Level": "Medium-Light", "Agtron": "58/75", "Est. Price": "$14.00/12 ounces", "Review Date": "October 2014", "Aroma": "8", "Acidity ": "8", "Body": "8", "Flavor": "8", "Aftertaste": "7"}, {"Roaster Location": "Thornton, Colorado", "Coffee Origin": "Gikongoro, Nyamagabe region, southern Rwanda.", "Roast Level": "Medium-Light", "Agtron": "56/70", "Est. Price": "NA", "Review Date": "October 2014", "Aroma": "8", "Acidity ": "7", "Body": "9", "Flavor": "8", "Aftertaste": "7"}, {"Roaster Location": "San Diego, California", "Coffee Origin": "Jinotega growing region, north-central Nicaragua.", "Roast Level": "Medium-Dark", "Agtron": "44/55", "Est. Price": "$14.57/16 ounces", "Review Date": "October 2014", "Aroma": "7", "Acidity ": "8", "Body": "8", "Flavor": "8", "Aftertaste": "7"}, {"Roaster Location": "Montreal, Quebec, Canada", "Coffee Origin": "Oaxaca State, Mexico.", "Roast Level": "Medium", "Agtron": "55/63", "Est. Price": "NA", "Review Date": "October 2014", "Aroma": "8", "Acidity ": "7", "Body": "8", "Flavor": "8", "Aftertaste": "7"}, {"Roaster Location": "Portland, Oregon", "Coffee Origin": "San Ignacio, northern Peru.", "Roast Level": "Medium", "Agtron": "50/57", "Est. Price": "NA", "Review Date": "October 2014", "Aroma": "8", "Acidity ": "7", "Body": "8", "Flavor": "8", "Aftertaste": "7"}, {"Roaster Location": "Sumner, Washington", "Coffee Origin": "Valle del Cauca Department, Colombia.", "Roast Level": "Medium", "Agtron": "52/64", "Est. Price": "$15.91/12 ounces", "Review Date": "October 2014", "Aroma": "8", "Acidity ": "7", "Body": "8", "Flavor": "7", "Aftertaste": "7"}, {"Roaster Location": "Driftless, Wisconsin", "Coffee Origin": "Kirinyaga County, central Kenya", "Roast Level": "Medium-Light", "Agtron": "61/79", "Est. Price": "$17.95/12 ounces", "Review Date": "October 2014", "Aroma": "9", "Acidity ": "8", "Body": "9", "Flavor": "9", "Aftertaste": "9"}, {"Roaster Location": "Driftless, Wisconsin", "Coffee Origin": "Gedeo Zone, Yirgacheffe growing region, southern Ethiopia.", "Roast Level": "Medium-Light", "Agtron": "59/75", "Est. Price": "$16.75/12 ounces", "Review Date": "October 2014", "Aroma": "9", "Acidity ": "9", "Body": "9", "Flavor": "9", "Aftertaste": "8"}, {"Roaster Location": "Driftless, Wisconsin", "Coffee Origin": "Gedeo Zone, Yirgacheffe growing region, southern Ethiopia.", "Roast Level": "Medium-Light", "Agtron": "57/75", "Est. Price": "$17.75/12 ounces", "Review Date": "October 2014", "Aroma": "8", "Acidity ": "8", "Body": "8", "Flavor": "9", "Aftertaste": "8"}, {"Roaster Location": "San Luis Obispo, California", "Coffee Origin": "Nyeri County, Central Highlands, Kenya.", "Roast Level": "Medium", "Agtron": "52/62", "Est. Price": "$18.00 / 12 ounces", "Review Date": "October 2014", "Aroma": "9", "Acidity ": "9", "Body": "8", "Flavor": "9", "Aftertaste": "9"}, {"Roaster Location": "Burlington, Vermont", "Coffee Origin": "Yirgacheffe growing region, southern Ethiopia.", "Roast Level": "Medium", "Agtron": "52/66", "Est. Price": "$9.00 / 8 ounces", "Review Date": "October 2014", "Aroma": "8", "Acidity ": "9", "Body": "8", "Flavor": "9", "Aftertaste": "8"}, {"Roaster Location": "Santa Monica, California", "Coffee Origin": "Nyeri County, central Kenya.", "Roast Level": "Medium-Dark", "Agtron": "45/54", "Est. Price": "$17.00/12 ounces", "Review Date": "October 2014", "Aroma": "8", "Acidity ": "8", "Body": "8", "Flavor": "8", "Aftertaste": "8"}, {"Roaster Location": "Dayton, Ohio", "Coffee Origin": "Murang’a County, Central Kenya.", "Roast Level": "Medium-Light", "Agtron": "60/79", "Est. Price": "$18.00/12 ounces", "Review Date": "October 2014", "Aroma": "8", "Acidity ": "8", "Body": "8", "Flavor": "8", "Aftertaste": "8"}, {"Roaster Location": "Topeka, Kansas", "Coffee Origin": "Konga District, Yirgacheffe growing region, southern Ethiopia.", "Roast Level": "Light", "Agtron": "62/84", "Est. Price": "$17.82/12 ounces", "Review Date": "October 2014", "Aroma": "9", "Acidity ": "8", "Body": "9", "Flavor": "10", "Aftertaste": "8"}, {"Roaster Location": "Yorktown Heights, New York", "Coffee Origin": "Nyeri County, Central Highlands, Kenya.", "Roast Level": "Medium-Light", "Agtron": "53/71", "Est. Price": "NA", "Review Date": "October 2014", "Aroma": "9", "Acidity ": "9", "Body": "9", "Flavor": "9", "Aftertaste": "8"}, {"Roaster Location": "Jackson, MIssissippi", "Coffee Origin": "Yirgacheffe growing region, southern Ethiopia.", "Roast Level": "Medium", "Agtron": "52/68", "Est. Price": "$14.00/12 ounces", "Review Date": "October 2014", "Aroma": "9", "Acidity ": "8", "Body": "9", "Flavor": "9", "Aftertaste": "9"}, {"Roaster Location": "Topeka, Kansas", "Coffee Origin": "Tarrazu growing region, Costa Rica.", "Roast Level": "Light", "Agtron": "61/82", "Est. Price": "$18.72/12 ounces", "Review Date": "October 2014", "Aroma": "8", "Acidity ": "9", "Body": "8", "Flavor": "9", "Aftertaste": "9"}, {"Roaster Location": "Madison, Wisconsin", "Coffee Origin": "Yirgacheffe growing region, south-central Ethiopia.", "Roast Level": "Medium-Light", "Agtron": "57/72", "Est. Price": "$14.50/12 ounces", "Review Date": "October 2014", "Aroma": "9", "Acidity ": "9", "Body": "8", "Flavor": "9", "Aftertaste": "8"}, {"Roaster Location": "Topeka, Kansas", "Coffee Origin": "Palencia, central Guatemala.", "Roast Level": "Light", "Agtron": "65/83", "Est. Price": "$20.46/12 ounces", "Review Date": "October 2014", "Aroma": "9", "Acidity ": "8", "Body": "8", "Flavor": "9", "Aftertaste": "8"}, {"Roaster Location": "Madison, Wisconsin", "Coffee Origin": "Francisco Morazán Department, central Honduras.", "Roast Level": "Light", "Agtron": "63/83", "Est. Price": "$14.25/12 ounces", "Review Date": "October 2014", "Aroma": "9", "Acidity ": "8", "Body": "7", "Flavor": "9", "Aftertaste": "8"}, {"Roaster Location": "Sacramento, California", "Coffee Origin": "Boke, Gamo Gofa Zone, Southern Ethiopia.", "Roast Level": "Medium-Light", "Agtron": "56/66", "Est. Price": "$17.50/12 ounces", "Review Date": "October 2014", "Aroma": "9", "Body": "9", "Flavor": "9", "Aftertaste": "8", "With Milk": "9"}, {"Roaster Location": "Minneapolis, Minnesota", "Coffee Origin": "Not disclosed.", "Roast Level": "Medium", "Agtron": "52/61", "Est. Price": "$15.99/16 ounces", "Review Date": "September 2014", "Aroma": "9", "Acidity ": "8", "Body": "8", "Flavor": "8", "Aftertaste": "8"}, {"Roaster Location": "Saint Paul, Minnesota", "Coffee Origin": "Valle de Cauca Department, western Colombia", "Roast Level": "Medium-Light", "Agtron": "55/68", "Est. Price": "$14.99/16 ounces", "Review Date": "September 2014", "Aroma": "8", "Acidity ": "8", "Body": "8", "Flavor": "8", "Aftertaste": "8"}, {"Roaster Location": "Ramsey, Minnesota", "Coffee Origin": "Lintong growing region, northern Sumatra, Indonesia.", "Roast Level": "Medium", "Agtron": "50/57", "Est. Price": "$13.95/12 ounces", "Review Date": "September 2014", "Aroma": "9", "Acidity ": "8", "Body": "8", "Flavor": "9", "Aftertaste": "9"}, {"Roaster Location": "Kansas City, Missouri", "Coffee Origin": "Gedeo Zone, Yirgacheffe growing region, southern Ethiopia.", "Roast Level": "Medium-Light", "Agtron": "55/69", "Est. Price": "$16.00/12 ounces", "Review Date": "September 2014", "Aroma": "9", "Acidity ": "8", "Body": "8", "Flavor": "10", "Aftertaste": "8"}, {"Roaster Location": "Kansas City, Missouri", "Coffee Origin": "Nyeri growing region, south-central Kenya.", "Roast Level": "Medium-Light", "Agtron": "58/65", "Est. Price": "$15.70/12 ounces", "Review Date": "September 2014", "Aroma": "9", "Acidity ": "8", "Body": "8", "Flavor": "9", "Aftertaste": "9"}, {"Roaster Location": "Madison, Wisconsin", "Coffee Origin": "Sidamo (also Sidama) growing region, southern Ethiopia.", "Roast Level": "Medium-Light", "Agtron": "56/72", "Est. Price": "$14.85/12 ounces", "Review Date": "September 2014", "Aroma": "9", "Body": "9", "Flavor": "9", "Aftertaste": "8", "With Milk": "9"}, {"Roaster Location": "Madison, Wisconsin", "Coffee Origin": "Sidamo (also Sidama) growing region, southern Ethiopia.", "Roast Level": "Medium-Light", "Agtron": "56/72", "Est. Price": "$14.85/12 ounces", "Review Date": "September 2014", "Aroma": "9", "Acidity ": "9", "Body": "8", "Flavor": "9", "Aftertaste": "8"}, {"Roaster Location": "Sacramento, California", "Coffee Origin": "San Luis de Grecia, central Costa Rica.", "Roast Level": "Light", "Agtron": "66/82", "Est. Price": "$17.00/12 ounces", "Review Date": "September 2014", "Aroma": "8", "Acidity ": "8", "Body": "8", "Flavor": "9", "Aftertaste": "8"}, {"Roaster Location": "San Diego, California", "Coffee Origin": "Nyeri County, Central Highlands, Kenya.", "Roast Level": "Medium", "Agtron": "50/55", "Est. Price": "$28.00/16 ounces", "Review Date": "September 2014", "Aroma": "9", "Acidity ": "9", "Body": "9", "Flavor": "9", "Aftertaste": "9"}, {"Roaster Location": "Pu’Er, Yunnan Province, China", "Coffee Origin": "Silla Del Pando, Volcan, Panama.", "Roast Level": "Medium-Light", "Agtron": "55/78", "Est. Price": "RMB 235/125 g", "Review Date": "September 2014", "Aroma": "9", "Acidity ": "9", "Body": "8", "Flavor": "9", "Aftertaste": "9"}, {"Roaster Location": "South Korea", "Coffee Origin": "Yirgacheffe growing region, southern Ethiopia.", "Roast Level": "Medium-Light", "Agtron": "59/74", "Est. Price": "KRW$10,500/100 grams", "Review Date": "September 2014", "Aroma": "9", "Acidity ": "9", "Body": "8", "Flavor": "10", "Aftertaste": "8"}, {"Roaster Location": "Sacr", "Coffee Origin": "Lintong growing region, northern Sumatra, Indonesia.", "Roast Level": "Medium", "Agtron": "54/66", "Est. Price": "$17.50/12 ounces", "Review Date": "September 2014", "Aroma": "9", "Acidity ": "8", "Body": "9", "Flavor": "9", "Aftertaste": "9"}, {"Roaster Location": "Topeka, Kansas", "Coffee Origin": "Ka'u growing district, \"Big Island\" of Hawaii.", "Roast Level": "Light", "Agtron": "68/89", "Est. Price": "$20.00/8 ounces", "Review Date": "September 2014", "Aroma": "8", "Acidity ": "9", "Body": "8", "Flavor": "9", "Aftertaste": "8"}, {"Roaster Location": "Topeka, Kansas", "Coffee Origin": "Valle del Cauca growing region, Colombia.", "Roast Level": "Light", "Agtron": "60/83", "Est. Price": "$20.00/8 ounces", "Review Date": "September 2014", "Aroma": "9", "Acidity ": "8", "Body": "9", "Flavor": "9", "Aftertaste": "8"}, {"Roaster Location": "Sacramento, California", "Coffee Origin": "Amaro region, southern Ethiopia.", "Roast Level": "Medium-Light", "Agtron": "58/76", "Est. Price": "$18.00/12 ounces", "Review Date": "September 2014", "Aroma": "9", "Acidity ": "8", "Body": "9", "Flavor": "9", "Aftertaste": "8"}, {"Roaster Location": "Tulsa, Oklahoma", "Coffee Origin": "Santa Ana Region, El Salvador.", "Roast Level": "Medium-Light", "Agtron": "56/75", "Est. Price": "$14.99/12 ounces", "Review Date": "September 2014", "Aroma": "8", "Acidity ": "8", "Body": "9", "Flavor": "9", "Aftertaste": "8"}, {"Roaster Location": "Los Angeles, California", "Coffee Origin": "Boquete growing region, western Panama.", "Roast Level": "Medium-Light", "Agtron": "58/80", "Est. Price": "$49.95/8 ounces", "Review Date": "September 2014", "Aroma": "10", "Acidity ": "9", "Body": "9", "Flavor": "10", "Aftertaste": "9"}, {"Roaster Location": "Boulder, Colorado", "Coffee Origin": "Boquete growing region, western Panama.", "Roast Level": "Medium-Light", "Agtron": "58/80", "Est. Price": "$18.00/12 ounces", "Review Date": "September 2014", "Aroma": "9", "Acidity ": "9", "Body": "9", "Flavor": "9", "Aftertaste": "8"}, {"Roaster Location": "Fort Bragg, California", "Coffee Origin": "Matagalpa growing region, Nicaragua.", "Roast Level": "Light", "Agtron": "64/80", "Est. Price": "$16.50/12 ounces", "Review Date": "September 2014", "Aroma": "9", "Acidity ": "9", "Body": "9", "Flavor": "9", "Aftertaste": "8"}, {"Roaster Location": "Los Angeles, California", "Coffee Origin": "Volcan growing region, western Panama.", "Roast Level": "Light", "Agtron": "72/87", "Est. Price": "$18.00/8 ounces", "Review Date": "September 2014", "Aroma": "9", "Acidity ": "9", "Body": "8", "Flavor": "9", "Aftertaste": "9"}, {"Roaster Location": "Sacramento, California", "Coffee Origin": "San Luis de Grecia, central Costa Rica.", "Roast Level": "Medium-Light", "Agtron": "57/74", "Est. Price": "$17.90/12 ounces", "Review Date": "September 2014", "Aroma": "9", "Acidity ": "9", "Body": "8", "Flavor": "9", "Aftertaste": "9"}, {"Roaster Location": "Tainan City, Taiwan", "Coffee Origin": "Boquete growing region, western Panama.", "Roast Level": "Medium-Light", "Agtron": "56/76", "Est. Price": "NT$ 480/8 ounces", "Review Date": "September 2014", "Aroma": "10", "Acidity ": "9", "Body": "8", "Flavor": "9", "Aftertaste": "8"}, {"Roaster Location": "Kowloon, Hong Kong, China", "Coffee Origin": "Tarrazu growing region, central Costa Rica.", "Roast Level": "Medium-Light", "Agtron": "57/79", "Est. Price": "HK $178/200 grams", "Review Date": "September 2014", "Aroma": "9", "Acidity ": "8", "Body": "9", "Flavor": "9", "Aftertaste": "9"}, {"Roaster Location": "Seoul, South Korea", "Coffee Origin": "Silla Del Pando, Volcan, Panama.", "Roast Level": "Medium-Light", "Agtron": "59/77", "Est. Price": "KRW 50,000/200 grams", "Review Date": "September 2014", "Aroma": "9", "Acidity ": "8", "Body": "9", "Flavor": "9", "Aftertaste": "9"}, {"Roaster Location": "Sacramento, California", "Coffee Origin": "Boquete growing region, western Panama.", "Roast Level": "Medium-Light", "Agtron": "56/79", "Est. Price": "$18.00/16 ounces", "Review Date": "September 2014", "Aroma": "9", "Acidity ": "8", "Body": "9", "Flavor": "9", "Aftertaste": "8"}, {"Roaster Location": "Minneapolis, Minnesota", "Coffee Origin": "Los Robles de Naranjo, West Valley, Costa Rica.", "Roast Level": "Light", "Agtron": "65/82", "Est. Price": "$18.00/12 ounces", "Review Date": "September 2014", "Aroma": "9", "Acidity ": "8", "Body": "9", "Flavor": "9", "Aftertaste": "8"}, {"Roaster Location": "San Rafael, California", "Coffee Origin": "Apaneca, Ahuachapan Department, El Salvador.", "Roast Level": "Medium", "Agtron": "52/69", "Est. Price": "$14.49/12 ounces", "Review Date": "September 2014", "Aroma": "9", "Acidity ": "8", "Body": "9", "Flavor": "9", "Aftertaste": "8"}, {"Roaster Location": "Seattle, Washington", "Coffee Origin": "Central Valley growing region, Costa Rica.", "Roast Level": "Medium-Light", "Agtron": "58/80", "Est. Price": "$17.45/12 ounces", "Review Date": "September 2014", "Aroma": "9", "Acidity ": "8", "Body": "9", "Flavor": "9", "Aftertaste": "8"}, {"Roaster Location": "Brooklyn, New York", "Coffee Origin": "Volcan de Santa Ana region, El Salvador.", "Roast Level": "Medium-Light", "Agtron": "59/78", "Est. Price": "$18.00/12 ounces", "Review Date": "August 2014", "Aroma": "8", "Acidity ": "9", "Body": "9", "Flavor": "9", "Aftertaste": "8"}, {"Roaster Location": "Chicago, Illinois", "Coffee Origin": "San Ignacio Acosta, Tarrazu growing region, central Costa Rica.", "Roast Level": "Medium-Light", "Agtron": "56/76", "Est. Price": "$17.50/12 ounces", "Review Date": "August 2014", "Aroma": "8", "Acidity ": "8", "Body": "9", "Flavor": "9", "Aftertaste": "9"}, {"Roaster Location": "Brooklyn, New York", "Coffee Origin": "La Libertad, Huehuetenango, Guatemala.", "Roast Level": "Medium-Light", "Agtron": "59/77", "Est. Price": "$18.00/12 ounces", "Review Date": "August 2014", "Aroma": "8", "Acidity ": "9", "Body": "9", "Flavor": "9", "Aftertaste": "8"}, {"Roaster Location": "Minneapolis, Minnesota", "Coffee Origin": "Central Kenya.", "Roast Level": "Medium", "Agtron": "52/66", "Est. Price": "$16.99/16 ounces", "Review Date": "August 2014", "Aroma": "9", "Acidity ": "8", "Body": "9", "Flavor": "9", "Aftertaste": "8"}, {"Roaster Location": "Hsinchu city, Taiwan", "Coffee Origin": "Yirgacheffe growing district, southern Ethiopia.", "Roast Level": "Light", "Agtron": "68/86", "Est. Price": "NTD $800/ 8 ounces", "Review Date": "August 2014", "Aroma": "9", "Acidity ": "9", "Body": "8", "Flavor": "9", "Aftertaste": "8"}, {"Roaster Location": "Los Angeles, California", "Coffee Origin": "Apaneca, Ataco, El Salvador.", "Roast Level": "Medium-Dark", "Agtron": "44/50", "Est. Price": "$15.95/12 ounces", "Review Date": "August 2014", "Aroma": "9", "Body": "9", "Flavor": "9", "Aftertaste": "8", "With Milk": "9"}, {"Roaster Location": "Kaohsiung City, Taiwan", "Coffee Origin": "Yirgacheffe growing region, southern Ethiopia.", "Roast Level": "Medium-Light", "Agtron": "53/70", "Est. Price": "TWD $1000/554 grams", "Review Date": "August 2014", "Aroma": "9", "Acidity ": "8", "Body": "9", "Flavor": "9", "Aftertaste": "8"}, {"Roaster Location": "Los Angeles, California", "Coffee Origin": "Cerro El Tigre, El Salvador.", "Roast Level": "Medium-Light", "Agtron": "57/75", "Est. Price": "$14.50/12 ounces", "Review Date": "August 2014", "Aroma": "9", "Acidity ": "8", "Body": "9", "Flavor": "9", "Aftertaste": "8"}, {"Roaster Location": "Kaohsiung City, Taiwan", "Coffee Origin": "Not disclosed.", "Roast Level": "Medium-Dark", "Agtron": "45/49", "Est. Price": "TWD $700/454 grams", "Review Date": "August 2014", "Aroma": "9", "Body": "8", "Flavor": "8", "Aftertaste": "7", "With Milk": "8"}, {"Roaster Location": "Kingston, Ontario, Canada", "Coffee Origin": "Not disclosed.", "Roast Level": "Dark", "Agtron": "36/45", "Est. Price": "$11.25/12 ounces", "Review Date": "August 2014", "Aroma": "9", "Body": "8", "Flavor": "9", "Aftertaste": "7", "With Milk": "8"}, {"Roaster Location": "Ramsey, Minnesota", "Coffee Origin": "Hawaiian Islands.", "Roast Level": "Medium-Dark", "Agtron": "49/52", "Est. Price": "$29.95/12 ounces", "Review Date": "August 2014", "Aroma": "9", "Body": "9", "Flavor": "9", "Aftertaste": "7", "With Milk": "9"}, {"Roaster Location": "Ramsey, Minnesota", "Coffee Origin": "Vera Cruz growing region, Mexico.", "Roast Level": "Medium-Light", "Agtron": "60/77", "Est. Price": "$14.95/12 ounces", "Review Date": "August 2014", "Aroma": "9", "Acidity ": "8", "Body": "9", "Flavor": "9", "Aftertaste": "7"}, {"Roaster Location": "Ramsey, Minnesota", "Coffee Origin": "Aceh growing region, northwestern Sumatra, Indonesia.", "Roast Level": "Medium", "Agtron": "48/57", "Est. Price": "$19.95/12 ounces", "Review Date": "August 2014", "Aroma": "8", "Acidity ": "7", "Body": "9", "Flavor": "9", "Aftertaste": "8"}, {"Roaster Location": "New Taipei City, Taiwan", "Coffee Origin": "Brazil; Ethiopia; Colombia.", "Roast Level": "Medium", "Agtron": "49/53", "Est. Price": "NA", "Review Date": "August 2014", "Aroma": "8", "Body": "9", "Flavor": "9", "Aftertaste": "8", "With Milk": "9"}, {"Roaster Location": "Clark, Wyoming", "Coffee Origin": "Nyeri growing region, south-central Kenya.", "Roast Level": "Medium", "Agtron": "52/63", "Est. Price": "$13.99/12 ounces", "Review Date": "August 2014", "Aroma": "8", "Acidity ": "8", "Body": "8", "Flavor": "9", "Aftertaste": "8"}, {"Roaster Location": "New Taipei City, Taiwan", "Coffee Origin": "Colombia; Indonesia; Ethiopia.", "Roast Level": "Medium-Dark", "Agtron": "46/51", "Est. Price": "NA", "Review Date": "August 2014", "Aroma": "8", "Body": "8", "Flavor": "9", "Aftertaste": "8", "With Milk": "9"}, {"Roaster Location": "Clark, Wyoming", "Coffee Origin": "South-central Kenya.", "Roast Level": "Dark", "Agtron": "0/70", "Est. Price": "$11.99/10 single-serve capsules", "Review Date": "August 2014", "Aroma": "8", "Acidity ": "8", "Body": "8", "Flavor": "8", "Aftertaste": "8"}, {"Roaster Location": "New Taipei City, Taiwan", "Coffee Origin": "Brazil; Colombia; Guatemala; Honduras.", "Roast Level": "Medium-Dark", "Agtron": "44/48", "Est. Price": "NA", "Review Date": "August 2014", "Aroma": "9", "Body": "8", "Flavor": "8", "Aftertaste": "7", "With Milk": "8"}, {"Roaster Location": "San Rafael, California", "Coffee Origin": "Ka'u growing district, \"Big Island\" of Hawaii.", "Roast Level": "Light", "Agtron": "70/85", "Est. Price": "$29.95/8 ounces", "Review Date": "August 2014", "Aroma": "9", "Acidity ": "9", "Body": "8", "Flavor": "9", "Aftertaste": "8"}, {"Roaster Location": "Fort Bragg, California", "Coffee Origin": "Kona growing region, “Big Island” of Hawaii.", "Roast Level": "Medium-Light", "Agtron": "50/73", "Est. Price": "$41.50/12 ounces", "Review Date": "August 2014", "Aroma": "9", "Acidity ": "9", "Body": "8", "Flavor": "9", "Aftertaste": "8"}, {"Roaster Location": "Pahala, Hawaii", "Coffee Origin": "Ka'u growing district, \"Big Island\" of Hawaii.", "Roast Level": "Medium", "Agtron": "53/67", "Est. Price": "$19.00/8 ounces", "Review Date": "August 2014", "Aroma": "9", "Acidity ": "8", "Body": "9", "Flavor": "9", "Aftertaste": "8"}, {"Roaster Location": "Holualoa, Hawaii", "Coffee Origin": "Holualoa, North Kona growing district, “Big Island” of Hawaii.", "Roast Level": "Medium-Light", "Agtron": "59/77", "Est. Price": "$32.95/8 ounces", "Review Date": "August 2014", "Aroma": "8", "Acidity ": "8", "Body": "9", "Flavor": "9", "Aftertaste": "8"}, {"Roaster Location": "Mountain View, Hawaii", "Coffee Origin": "Puna District, \"Big Island\" of Hawaii.", "Roast Level": "Medium-Light", "Agtron": "56/68", "Est. Price": "$18.00/8 ounces", "Review Date": "August 2014", "Aroma": "9", "Acidity ": "8", "Body": "8", "Flavor": "9", "Aftertaste": "8", "With Milk": "5"}, {"Roaster Location": "San Diego, California", "Coffee Origin": "Kona growing region, “Big Island” of Hawaii.", "Roast Level": "Medium", "Agtron": "53/65", "Est. Price": "$35.00/8 ounces", "Review Date": "August 2014", "Aroma": "9", "Acidity ": "8", "Body": "9", "Flavor": "9", "Aftertaste": "8"}, {"Roaster Location": "Honolulu, Hawaii", "Coffee Origin": "Kona growing region, “Big Island” of Hawaii.", "Roast Level": "Medium", "Agtron": "50/69", "Est. Price": "$27.40/7 ounces", "Review Date": "August 2014", "Aroma": "8", "Acidity ": "8", "Body": "9", "Flavor": "9", "Aftertaste": "7"}, {"Roaster Location": "Kailua, Kona", "Coffee Origin": "Waialua, Oahu, Hawaii.", "Roast Level": "Medium-Light", "Agtron": "59/68", "Est. Price": "$17.50/8 ounces", "Review Date": "August 2014", "Aroma": "8", "Acidity ": "8", "Body": "8", "Flavor": "8", "Aftertaste": "8"}, {"Roaster Location": "Terrace, British Colombia, Canada", "Coffee Origin": "Ka'anapali, Maui, Hawaii.", "Roast Level": "Medium-Light", "Agtron": "53/75", "Est. Price": "CAD $15.95/12 ounces", "Review Date": "August 2014", "Aroma": "8", "Acidity ": "8", "Body": "8", "Flavor": "8", "Aftertaste": "8"}, {"Roaster Location": "Trumbull, Connecticut", "Coffee Origin": "Aleta Wondo, Sidama growing region, Ethiopia.", "Roast Level": "Medium-Light", "Agtron": "54/68", "Est. Price": "$15.00/12 ounces", "Review Date": "August 2014", "Aroma": "9", "Acidity ": "8", "Body": "9", "Flavor": "9", "Aftertaste": "7"}, {"Roaster Location": "Sacramento, California", "Coffee Origin": "Boquete growing region, western Panama.", "Roast Level": "Medium", "Agtron": "50/70", "Est. Price": "$18.00/12 ounces", "Review Date": "August 2014", "Aroma": "9", "Acidity ": "8", "Body": "9", "Flavor": "9", "Aftertaste": "8"}, {"Roaster Location": "Madison, Wisconsin", "Coffee Origin": "South-central Kenya.", "Roast Level": "Medium-Light", "Agtron": "58/73", "Est. Price": "$19.95/12 ounces", "Review Date": "July 2014", "Aroma": "9", "Acidity ": "9", "Body": "9", "Flavor": "9", "Aftertaste": "8"}, {"Roaster Location": "Madison, Wisconsin", "Coffee Origin": "Yirgacheffe growing district, southern Ethiopia.", "Roast Level": "Medium-Light", "Agtron": "56/76", "Est. Price": "$16.85/12 ounces", "Review Date": "July 2014", "Aroma": "8", "Acidity ": "9", "Body": "9", "Flavor": "9", "Aftertaste": "8"}, {"Roaster Location": "Madison, Wisconsin", "Coffee Origin": "South-central Kenya.", "Roast Level": "Medium-Light", "Agtron": "58/73", "Est. Price": "$19.95/12 ounces", "Review Date": "July 2014", "Aroma": "8", "Body": "9", "Flavor": "9", "Aftertaste": "8", "With Milk": "9"}]