[{"Roaster Location": "San Diego, California", "Coffee Origin": "Huila Department, southern Colombia", "Roast Level": "Light", "Agtron": "63/85", "Est. Price": "$17.00/12 ounces", "Review Date": "January 2018", "Aroma": "8", "Acidity /Structure ": "9", "Body": "8", "Flavor": "9", "Aftertaste": "8"}, {"Roaster Location": "Taichung, Taiwan", "Coffee Origin": "Acatenango growing region, central Guatemala", "Roast Level": "Light", "Agtron": "60/86", "Est. Price": "$35.00/100 grams", "Review Date": "January 2018", "Aroma": "9", "Acidity /Structure ": "8", "Body": "9", "Flavor": "9", "Aftertaste": "8"}, {"Roaster Location": "San Diego, California", "Coffee Origin": "Piedra Candela, Chiriqui Province, far western Panama", "Roast Level": "Medium-Light", "Agtron": "53/81", "Est. Price": "$51.00/8 ounces", "Review Date": "January 2018", "Aroma": "10", "Acidity /Structure ": "9", "Body": "9", "Flavor": "9", "Aftertaste": "8"}, {"Roaster Location": "Hong Kong, China", "Coffee Origin": "Gayo (also Aceh) growing region, Aceh Province, northern Sumatra, Indonesia", "Roast Level": "Medium-Light", "Agtron": "54/78", "Est. Price": "HKD $140/227 grams", "Review Date": "January 2018", "Aroma": "9", "Acidity /Structure ": "8", "Body": "8", "Flavor": "9", "Aftertaste": "8"}, {"Roaster Location": "Sacramento, California", "Coffee Origin": "Chiriqui Province, far western Panama", "Roast Level": "Light", "Agtron": "60/84", "Est. Price": "$54.00/8 ounces", "Review Date": "January 2018", "Aroma": "9", "Acidity /Structure ": "9", "Body": "9", "Flavor": "9", "Aftertaste": "9"}, {"Roaster Location": "Sacramento, California", "Coffee Origin": "Yirgacheffe growing region, southern Ethiopia", "Roast Level": "Medium-Light", "Agtron": "54/74", "Est. Price": "$19.00/12 ounces", "Review Date": "January 2018", "Aroma": "9", "Acidity /Structure ": "7", "Body": "8", "Flavor": "9", "Aftertaste": "9"}, {"Roaster Location": "Sacramento, California", "Coffee Origin": "Central Valley, Costa Rica", "Roast Level": "Medium-Light", "Agtron": "53/87", "Est. Price": "$20.50/12 ounces", "Review Date": "January 2018", "Aroma": "8", "Acidity /Structure ": "8", "Body": "8", "Flavor": "9", "Aftertaste": "8"}, {"Roaster Location": "Taoyuan City, Taiwan", "Coffee Origin": "Yirgacheffe growing region, southern Ethiopia", "Roast Level": "Medium-Dark", "Agtron": "40/60", "Est. Price": "NT $1300/16 ounces", "Review Date": "January 2018", "Aroma": "9", "Body": "9", "Flavor": "9", "Aftertaste": "9", "With Milk": "9"}, {"Roaster Location": "Charlotte, North Carolina", "Coffee Origin": "Brazil and four other origins", "Roast Level": "Medium-Light", "Agtron": "56/72", "Est. Price": "$14.00/12 ounces", "Review Date": "January 2018", "Aroma": "9", "Body": "9", "Flavor": "9", "Aftertaste": "8", "With Milk": "9"}, {"Roaster Location": "Pahala, Hawaii", "Coffee Origin": "Ka'u growing region, Big Island of Hawaii", "Roast Level": "Medium-Light", "Agtron": "61/77", "Est. Price": "$29.48/8 ounces", "Review Date": "January 2018", "Aroma": "9", "Acidity /Structure ": "8", "Body": "8", "Flavor": "9", "Aftertaste": "9"}, {"Roaster Location": "Taoyuan City, Taiwan", "Coffee Origin": "Yirgacheffe growing region, southern Ethiopia", "Roast Level": "Medium", "Agtron": "47/69", "Est. Price": "NT $2500/16 ounces", "Review Date": "January 2018", "Aroma": "9", "Body": "9", "Flavor": "9", "Aftertaste": "7", "With Milk": "9"}, {"Roaster Location": "Taichung, Taiwan", "Coffee Origin": "Guji Zone, southern Ethiopia", "Roast Level": "Light", "Agtron": "57/85", "Est. Price": "$35.00/100 grams", "Review Date": "January 2018", "Aroma": "9", "Acidity /Structure ": "8", "Body": "9", "Flavor": "9", "Aftertaste": "8"}, {"Roaster Location": "Santa Rosa Beach, Florida", "Coffee Origin": "Gatundu, Thika Province, central Kenya", "Roast Level": "Medium-Light", "Agtron": "54/80", "Est. Price": "$19.95/8 ounces", "Review Date": "December 2017", "Aroma": "9", "Acidity /Structure ": "8", "Body": "9", "Flavor": "9", "Aftertaste": "7"}, {"Roaster Location": "Ramsey, Minnesota", "Coffee Origin": "Not disclosed", "Roast Level": "Medium", "Agtron": "46/67", "Est. Price": "$12.95/12 ounces", "Review Date": "December 2017", "Aroma": "8", "Body": "9", "Flavor": "9", "Aftertaste": "8", "With Milk": "9"}, {"Roaster Location": "Ramsey, Minnesota", "Coffee Origin": "Doi Pangkhon growing region, northern Thailand", "Roast Level": "Medium", "Agtron": "50/68", "Est. Price": "$16.95/12 ounces", "Review Date": "December 2017", "Aroma": "8", "Body": "8", "Flavor": "9", "Aftertaste": "8", "With Milk": "8"}, {"Roaster Location": "Madison, Wisconsin", "Coffee Origin": "Northern Sumatra, Indonesia", "Roast Level": "Medium-Light", "Agtron": "54/76", "Est. Price": "$18.95/12 ounces", "Review Date": "December 2017", "Aroma": "9", "Acidity /Structure ": "9", "Body": "9", "Flavor": "10", "Aftertaste": "9"}, {"Roaster Location": "Madison, Wisconsin", "Coffee Origin": "Southern Tolima Department, west-central Colombia", "Roast Level": "Light", "Agtron": "58/84", "Est. Price": "$15.75/12 ounces", "Review Date": "December 2017", "Aroma": "9", "Acidity /Structure ": "8", "Body": "8", "Flavor": "9", "Aftertaste": "7"}, {"Roaster Location": "Topeka, Kansas", "Coffee Origin": "Boquete growing region, western Panama", "Roast Level": "Medium-Light", "Agtron": "53/85", "Est. Price": "$60.00/8 ounces", "Review Date": "December 2017", "Aroma": "9", "Acidity /Structure ": "9", "Body": "9", "Flavor": "9", "Aftertaste": "9"}, {"Roaster Location": "Topeka, Kansas", "Coffee Origin": "Piedra Candela, Chiriqui Province, far western Panama", "Roast Level": "Light", "Agtron": "63/85", "Est. Price": "$40.00/8 ounces", "Review Date": "December 2017", "Aroma": "8", "Acidity /Structure ": "9", "Body": "9", "Flavor": "9", "Aftertaste": "8"}, {"Roaster Location": "Topeka, Kansas", "Coffee Origin": "Haraz growing region, north-central Yemen", "Roast Level": "Light", "Agtron": "62/84", "Est. Price": "$27.50/8 ounces", "Review Date": "December 2017", "Aroma": "9", "Acidity /Structure ": "8", "Body": "8", "Flavor": "9", "Aftertaste": "8"}, {"Roaster Location": "Portland, Oregon", "Coffee Origin": "Kiambu County, south-central Kenya", "Roast Level": "Light", "Agtron": "58/84", "Est. Price": "$15.00/250 grams", "Review Date": "December 2017", "Aroma": "9", "Acidity /Structure ": "9", "Body": "9", "Flavor": "10", "Aftertaste": "9"}, {"Roaster Location": "Captain Cook, Hawaii", "Coffee Origin": "Captain Cook, North Kona growing district, “Big Island” of Hawaii", "Roast Level": "Medium-Light", "Agtron": "54/78", "Est. Price": "$30.00/8 ounces", "Review Date": "December 2017", "Aroma": "9", "Acidity /Structure ": "8", "Body": "8", "Flavor": "9", "Aftertaste": "8"}, {"Roaster Location": "Sacramento, California", "Coffee Origin": "Chimaltenango Department, Guatemala", "Roast Level": "Light", "Agtron": "58/84", "Est. Price": "$17.00/12 ounces", "Review Date": "December 2017", "Aroma": "9", "Acidity /Structure ": "8", "Body": "9", "Flavor": "9", "Aftertaste": "8"}, {"Roaster Location": "Lee, Massachusetts", "Coffee Origin": "Jinotega, Nicaragua", "Roast Level": "Light", "Agtron": "61/93", "Est. Price": "$17.95/12 ounces", "Review Date": "December 2017", "Aroma": "9", "Acidity /Structure ": "9", "Body": "8", "Flavor": "9", "Aftertaste": "9"}, {"Roaster Location": "Portland, Maine", "Coffee Origin": "Mukaro, Nyeri growing region, south-central Kenya", "Roast Level": "Medium-Light", "Agtron": "50/76", "Est. Price": "$20.00/12 ounces", "Review Date": "December 2017", "Aroma": "9", "Acidity /Structure ": "9", "Body": "9", "Flavor": "9", "Aftertaste": "9"}, {"Roaster Location": "Chia-Yi, Taiwan", "Coffee Origin": "Marcala growing region, La Paz Department, Honduras", "Roast Level": "Medium-Light", "Agtron": "53/77", "Est. Price": "NT $500/16 ounces", "Review Date": "December 2017", "Aroma": "9", "Body": "8", "Flavor": "9", "Aftertaste": "8", "With Milk": "9"}, {"Roaster Location": "Chino, California", "Coffee Origin": "Kiambu County, south-central Kenya", "Roast Level": "Medium-Light", "Agtron": "53/79", "Est. Price": "$25.00/12 ounces", "Review Date": "December 2017", "Aroma": "9", "Acidity /Structure ": "8", "Body": "8", "Flavor": "9", "Aftertaste": "8"}, {"Roaster Location": "Chia-Yi, Taiwan", "Coffee Origin": "Copan, Honduras", "Roast Level": "Medium-Light", "Agtron": "55/79", "Est. Price": "NT $500/16 ounces", "Review Date": "December 2017", "Aroma": "9", "Body": "8", "Flavor": "8", "Aftertaste": "8", "With Milk": "9"}, {"Roaster Location": "San Diego, California", "Coffee Origin": "Kiambu County, south-central Kenya", "Roast Level": "Medium-Light", "Agtron": "50/74", "Est. Price": "$24.00/12 ounces", "Review Date": "December 2017", "Aroma": "8", "Acidity /Structure ": "8", "Body": "8", "Flavor": "9", "Aftertaste": "8"}, {"Roaster Location": "Chino, California", "Coffee Origin": "Huila, Colombia", "Roast Level": "Medium", "Agtron": "48/58", "Est. Price": "$16.95/12 ounces", "Review Date": "December 2017", "Aroma": "8", "Acidity /Structure ": "8", "Body": "8", "Flavor": "8", "Aftertaste": "7"}, {"Roaster Location": "Montrose, Colorado", "Coffee Origin": "Muranga District, central Kenya", "Roast Level": "Medium-Light", "Agtron": "55/77", "Est. Price": "$14.00/250 grams", "Review Date": "December 2017", "Aroma": "9", "Acidity /Structure ": "9", "Body": "9", "Flavor": "9", "Aftertaste": "9"}, {"Roaster Location": "Spokane, Washington", "Coffee Origin": "Yirgacheffe growing region, southern Ethiopia", "Roast Level": "Medium-Light", "Agtron": "56/84", "Est. Price": "$25.00/12 ounces", "Review Date": "December 2017", "Aroma": "9", "Acidity /Structure ": "8", "Body": "9", "Flavor": "9", "Aftertaste": "8"}, {"Roaster Location": "Floyd, Virginia", "Coffee Origin": "Ethiopia; Kenya; Colombia", "Roast Level": "Medium-Light", "Agtron": "57/81", "Est. Price": "$14.99/12 ounces", "Review Date": "December 2017", "Aroma": "9", "Acidity /Structure ": "8", "Body": "9", "Flavor": "9", "Aftertaste": "8"}, {"Roaster Location": "Portland, Maine", "Coffee Origin": "Kirumba, North Kivu Province, Democratic Republic of the Congo", "Roast Level": "Medium-Light", "Agtron": "58/82", "Est. Price": "$17.00/12 ounces", "Review Date": "December 2017", "Aroma": "9", "Acidity /Structure ": "8", "Body": "9", "Flavor": "9", "Aftertaste": "8"}, {"Roaster Location": "Hsinchu, Taiwan", "Coffee Origin": "Ethiopia; Costa Rica; Panama", "Roast Level": "Light", "Agtron": "58/86", "Est. Price": "$22.00/8 ounces", "Review Date": "December 2017", "Aroma": "9", "Acidity /Structure ": "9", "Body": "8", "Flavor": "9", "Aftertaste": "8"}, {"Roaster Location": "Louisville, Kentucky", "Coffee Origin": "Nakuru County, south-central Kenya", "Roast Level": "Medium-Light", "Agtron": "54/78", "Est. Price": "$22.00/12 ounces", "Review Date": "December 2017", "Aroma": "9", "Acidity /Structure ": "9", "Body": "9", "Flavor": "9", "Aftertaste": "9"}, {"Roaster Location": "Bedford, New Hampshire", "Coffee Origin": "Kirinyaga District, south-central Kenya", "Roast Level": "Medium-Light", "Agtron": "56/80", "Est. Price": "$15.00/12 ounces", "Review Date": "December 2017", "Aroma": "9", "Acidity /Structure ": "9", "Body": "9", "Flavor": "9", "Aftertaste": "8"}, {"Roaster Location": "Boulder, Colorado", "Coffee Origin": "Nueva Segovia growing region, Nicaragua", "Roast Level": "Light", "Agtron": "58/84", "Est. Price": "$20.00/12 ounces", "Review Date": "December 2017", "Aroma": "9", "Acidity /Structure ": "8", "Body": "9", "Flavor": "9", "Aftertaste": "8"}, {"Roaster Location": "Highland Park, New Jersey", "Coffee Origin": "Biolley, southern Costa Rica", "Roast Level": "Medium-Light", "Agtron": "53/77", "Est. Price": "$28.00/8 ounces", "Review Date": "December 2017", "Aroma": "9", "Acidity /Structure ": "9", "Body": "8", "Flavor": "9", "Aftertaste": "8"}, {"Roaster Location": "Taipei, Taiwan", "Coffee Origin": "Kochere, Yirgacheffe growing region, south-central Ethiopia", "Roast Level": "Light", "Agtron": "58/86", "Est. Price": "NT $580/220 grams", "Review Date": "December 2017", "Aroma": "9", "Acidity /Structure ": "9", "Body": "9", "Flavor": "9", "Aftertaste": "8"}, {"Roaster Location": "Branford, Connecticut", "Coffee Origin": "Piedra Candela, Chiriqui Province, far western Panama", "Roast Level": "Medium-Light", "Agtron": "56/80", "Est. Price": "$55.00/12 ounces", "Review Date": "December 2017", "Aroma": "10", "Acidity /Structure ": "9", "Body": "9", "Flavor": "9", "Aftertaste": "9"}, {"Roaster Location": "San Diego, California", "Coffee Origin": "Santa Ana Department, El Salvador", "Roast Level": "Medium-Light", "Agtron": "56/80", "Est. Price": "$25.00/12 ounces", "Review Date": "December 2017", "Aroma": "9", "Acidity /Structure ": "9", "Body": "9", "Flavor": "9", "Aftertaste": "9"}, {"Roaster Location": "San Rafael, California", "Coffee Origin": "Boquete growing region, western Panama", "Roast Level": "Medium-Light", "Agtron": "53/77", "Est. Price": "$37.00/4 ounces", "Review Date": "December 2017", "Aroma": "9", "Acidity /Structure ": "9", "Body": "8", "Flavor": "9", "Aftertaste": "9"}, {"Roaster Location": "Madison, Wisconsin", "Coffee Origin": "South-central Kenya", "Roast Level": "Medium-Light", "Agtron": "55/76", "Est. Price": "$19.25/12 ounces", "Review Date": "November 2017", "Aroma": "9", "Acidity /Structure ": "10", "Body": "9", "Flavor": "9", "Aftertaste": "9"}, {"Roaster Location": "Branford, Connecticut", "Coffee Origin": "Horcheta, Chiriqui Province, western Panama", "Roast Level": "Medium-Light", "Agtron": "56/80", "Est. Price": "$49.99/16 ounces", "Review Date": "November 2017", "Aroma": "9", "Acidity /Structure ": "9", "Body": "9", "Flavor": "9", "Aftertaste": "9"}, {"Roaster Location": "Holualoa, Hawaii", "Coffee Origin": "Holualoa, North Kona growing district, “Big Island” of Hawaii", "Roast Level": "Medium-Light", "Agtron": "52/76", "Est. Price": "$44.95/8 ounces", "Review Date": "November 2017", "Aroma": "9", "Acidity /Structure ": "9", "Body": "9", "Flavor": "9", "Aftertaste": "9"}, {"Roaster Location": "Los Angeles, California", "Coffee Origin": "Nyeri growing region, south-central Kenya", "Roast Level": "Medium-Light", "Agtron": "55/75", "Est. Price": "$19.95/12 ounces", "Review Date": "November 2017", "Aroma": "9", "Acidity /Structure ": "9", "Body": "9", "Flavor": "10", "Aftertaste": "8"}, {"Roaster Location": "Ramsey, Minnesota", "Coffee Origin": "Narino Department, southern Colombia", "Roast Level": "Medium-Light", "Agtron": "54/74", "Est. Price": "$16.95/12 ounces", "Review Date": "November 2017", "Aroma": "8", "Acidity /Structure ": "9", "Body": "9", "Flavor": "9", "Aftertaste": "8"}, {"Roaster Location": "Newtown, Sydney, Australia", "Coffee Origin": "Paso Ancho, Volcan, western Panama", "Roast Level": "Medium-Light", "Agtron": "54/78", "Est. Price": "AUD $48.00/200 grams", "Review Date": "November 2017", "Aroma": "9", "Acidity /Structure ": "9", "Body": "9", "Flavor": "10", "Aftertaste": "8"}, {"Roaster Location": "St. Paul, Minnesota", "Coffee Origin": "Colombia", "Roast Level": "Medium-Light", "Agtron": "54/76", "Est. Price": "$15.00/12 ounces", "Review Date": "November 2017", "Aroma": "7", "Acidity /Structure ": "7", "Body": "8", "Flavor": "8", "Aftertaste": "7"}, {"Roaster Location": "Ramsey, Minnesota", "Coffee Origin": "Yirgacheffe, Ethiopia; Sidamo (also Sidama), Ethiopia", "Roast Level": "Medium-Light", "Agtron": "56/76", "Est. Price": "$17.95/12 ounces", "Review Date": "November 2017", "Aroma": "9", "Acidity /Structure ": "8", "Body": "9", "Flavor": "9", "Aftertaste": "8"}, {"Roaster Location": "Miami, Florida", "Coffee Origin": "Indonesia; Central and South America", "Roast Level": "Very Dark", "Agtron": "0/37", "Est. Price": "$7.50/12 capsules", "Review Date": "November 2017", "Aroma": "8", "Acidity /Structure ": "7", "Body": "9", "Flavor": "8", "Aftertaste": "7"}, {"Roaster Location": "Holualoa, Hawaii", "Coffee Origin": "Holualoa, North Kona growing district, “Big Island” of Hawaii", "Roast Level": "Medium-Light", "Agtron": "56/78", "Est. Price": "$74.95/8 ounces", "Review Date": "November 2017", "Aroma": "10", "Acidity /Structure ": "9", "Body": "9", "Flavor": "10", "Aftertaste": "9"}, {"Roaster Location": "Chia-Yi, Taiwan", "Coffee Origin": "Kirinyaga District, south-central Kenya", "Roast Level": "Medium-Light", "Agtron": "54/76", "Est. Price": "NT $650/16 ounces", "Review Date": "November 2017", "Aroma": "9", "Acidity /Structure ": "9", "Body": "9", "Flavor": "9", "Aftertaste": "9"}, {"Roaster Location": "Thermopolis, Wyoming", "Coffee Origin": "Nyeri growing region, south-central Kenya", "Roast Level": "Medium-Dark", "Agtron": "38/52", "Est. Price": "$18.00/12 ounces", "Review Date": "November 2017", "Aroma": "9", "Acidity /Structure ": "8", "Body": "8", "Flavor": "9", "Aftertaste": "8"}, {"Roaster Location": "Chia-Yi, Taiwan", "Coffee Origin": "Yirgacheffe growing region, southern Ethiopia", "Roast Level": "Medium-Light", "Agtron": "56/78", "Est. Price": "NT $550/16 ounces", "Review Date": "November 2017", "Aroma": "9", "Acidity /Structure ": "9", "Body": "9", "Flavor": "9", "Aftertaste": "9"}, {"Roaster Location": "Toronto, Ontario, Canada", "Coffee Origin": "Mexico, Ethiopia, Brazil", "Roast Level": "Medium-Light", "Agtron": "51/73", "Est. Price": "CAD $18.00/12 ounces", "Review Date": "November 2017", "Aroma": "9", "Body": "8", "Flavor": "9", "Aftertaste": "8", "With Milk": "9"}, {"Roaster Location": "Toronto, Ontario, Canada", "Coffee Origin": "Mexico; Ethiopia", "Roast Level": "Medium-Light", "Agtron": "52/74", "Est. Price": "CAD $18.00/12 ounces", "Review Date": "November 2017", "Aroma": "9", "Body": "9", "Flavor": "9", "Aftertaste": "8", "With Milk": "9"}, {"Roaster Location": "Toronto, Ontario, Canada", "Coffee Origin": "Nakuru Province, south-central Kenya", "Roast Level": "Medium-Light", "Agtron": "54/80", "Est. Price": "CAD $21.00/12 ounces", "Review Date": "November 2017", "Aroma": "9", "Acidity /Structure ": "9", "Body": "9", "Flavor": "9", "Aftertaste": "8"}, {"Roaster Location": "Sacramento, California", "Coffee Origin": "San Martin Jilotepeque, Chimaltenango Department, Guatemala", "Roast Level": "Light", "Agtron": "71/99", "Est. Price": "$19.00/12 ounces", "Review Date": "November 2017", "Aroma": "9", "Acidity /Structure ": "8", "Body": "8", "Flavor": "9", "Aftertaste": "9"}, {"Roaster Location": "Santa Monica, California", "Coffee Origin": "Kericho County, Kenya", "Roast Level": "Medium-Light", "Agtron": "52/76", "Est. Price": "$20.00/12 ounces", "Review Date": "November 2017", "Aroma": "8", "Acidity /Structure ": "8", "Body": "9", "Flavor": "9", "Aftertaste": "8"}, {"Roaster Location": "Chino, California", "Coffee Origin": "Santa Rosa, La Unión Department, El Salvador", "Roast Level": "Medium-Light", "Agtron": "55/77", "Est. Price": "$11.90/12 ounces", "Review Date": "November 2017", "Aroma": "8", "Acidity /Structure ": "7", "Body": "8", "Flavor": "8", "Aftertaste": "8"}, {"Roaster Location": "Lexington, Virginia", "Coffee Origin": "Gichugu Division, Kirinyaga County, central Kenya", "Roast Level": "Medium-Light", "Agtron": "52/74", "Est. Price": "$19.95/12 ounces", "Review Date": "November 2017", "Aroma": "8", "Acidity /Structure ": "9", "Body": "9", "Flavor": "9", "Aftertaste": "8"}, {"Roaster Location": "Hamilton, Montana", "Coffee Origin": "Yirgacheffe growing region, southern Ethiopia", "Roast Level": "Medium-Light", "Agtron": "50/74", "Est. Price": "$15.00/12 ounces", "Review Date": "November 2017", "Aroma": "9", "Acidity /Structure ": "7", "Body": "9", "Flavor": "9", "Aftertaste": "8"}, {"Roaster Location": "Clark, Wyoming", "Coffee Origin": "Not disclosed", "Roast Level": "Medium", "Agtron": "44/66", "Est. Price": "$14.99/12 ounces", "Review Date": "November 2017", "Aroma": "8", "Acidity /Structure ": "8", "Body": "8", "Flavor": "9", "Aftertaste": "8"}, {"Roaster Location": "Clark, Wyoming", "Coffee Origin": "Not disclosed", "Roast Level": "Medium", "Agtron": "42/66", "Est. Price": "$14.99/12 ounces", "Review Date": "November 2017", "Aroma": "8", "Acidity /Structure ": "8", "Body": "8", "Flavor": "8", "Aftertaste": "8"}, {"Roaster Location": "Ashland, Oregon", "Coffee Origin": "Hambela District, Guji Zone, Oromia Region, southern Ethiopia", "Roast Level": "Light", "Agtron": "63/97", "Est. Price": "$19.00/12 ounces", "Review Date": "November 2017", "Aroma": "8", "Acidity /Structure ": "9", "Body": "8", "Flavor": "9", "Aftertaste": "9"}, {"Roaster Location": "Portland, Oregon", "Coffee Origin": "Aleta Wondo, Sidama (also Sidamo) growing region, southern Ethiopia", "Roast Level": "Light", "Agtron": "62/92", "Est. Price": "$16.00/12 ounces", "Review Date": "November 2017", "Aroma": "9", "Acidity /Structure ": "9", "Body": "8", "Flavor": "9", "Aftertaste": "8"}, {"Roaster Location": "Putnam, Connecticut", "Coffee Origin": "Yirgacheffe growing region, southern Ethiopia", "Roast Level": "Medium-Light", "Agtron": "52/74", "Est. Price": "$16.95/12 ounces", "Review Date": "November 2017", "Aroma": "9", "Acidity /Structure ": "8", "Body": "8", "Flavor": "9", "Aftertaste": "8"}, {"Roaster Location": "Billings, Montana", "Coffee Origin": "Guji Zone, southern Ethiopia", "Roast Level": "Medium-Light", "Agtron": "54/70", "Est. Price": "$16.00/12 ounces", "Review Date": "November 2017", "Aroma": "9", "Acidity /Structure ": "8", "Body": "8", "Flavor": "9", "Aftertaste": "8"}, {"Roaster Location": "Spokane, Washington", "Coffee Origin": "Guji Zone, Oromia Region, south-central Ethiopia", "Roast Level": "Medium-Light", "Agtron": "53/79", "Est. Price": "$19.00/16 ounces", "Review Date": "November 2017", "Aroma": "8", "Acidity /Structure ": "8", "Body": "9", "Flavor": "9", "Aftertaste": "8"}, {"Roaster Location": "Hamilton, Montana", "Coffee Origin": "Gedeb District, Gedeo Zone, southern Ethiopia", "Roast Level": "Medium", "Agtron": "48/70", "Est. Price": "$16.50/12 ounces", "Review Date": "November 2017", "Aroma": "9", "Acidity /Structure ": "9", "Body": "9", "Flavor": "9", "Aftertaste": "8"}, {"Roaster Location": "Floyd, Virginia", "Coffee Origin": "Odo Shakiso District, Guji Zone, southern Ethiopia", "Roast Level": "Light", "Agtron": "66/92", "Est. Price": "$17.49/12 ounces", "Review Date": "November 2017", "Aroma": "9", "Acidity /Structure ": "8", "Body": "9", "Flavor": "9", "Aftertaste": "8"}, {"Roaster Location": "Branford, Connecticut", "Coffee Origin": "Yirgacheffe growing region, southern Ethiopia", "Roast Level": "Medium-Light", "Agtron": "54/75", "Est. Price": "$17.99/16 ounces", "Review Date": "November 2017", "Aroma": "9", "Acidity /Structure ": "8", "Body": "9", "Flavor": "9", "Aftertaste": "8"}, {"Roaster Location": "Ukiah, California", "Coffee Origin": "Hambela Wamena District, Guji Zone, Oromia Region, southern Ethiopia", "Roast Level": "Medium-Light", "Agtron": "58/80", "Est. Price": "$17.50/12 ounces", "Review Date": "November 2017", "Aroma": "9", "Acidity /Structure ": "8", "Body": "9", "Flavor": "9", "Aftertaste": "8"}, {"Roaster Location": "Driftless, Wisconsin", "Coffee Origin": "Hambela District, Guji Zone, Oromia Region, southern Ethiopia", "Roast Level": "Medium-Light", "Agtron": "58/81", "Est. Price": "$18.00/12 ounces", "Review Date": "November 2017", "Aroma": "9", "Acidity /Structure ": "9", "Body": "8", "Flavor": "9", "Aftertaste": "8"}, {"Roaster Location": "Oakville, Ontario, Canada", "Coffee Origin": "Sidama (also Sidamo) growing region, southern Ethiopia", "Roast Level": "Medium", "Agtron": "47/72", "Est. Price": "CAD $17.00/12 ounces", "Review Date": "November 2017", "Aroma": "9", "Acidity /Structure ": "9", "Body": "9", "Flavor": "9", "Aftertaste": "8"}, {"Roaster Location": "Topeka, Kansas", "Coffee Origin": "Central Kenya", "Roast Level": "Medium", "Agtron": "47/65", "Est. Price": "$24.50/12 ounces", "Review Date": "November 2017", "Aroma": "9", "Acidity /Structure ": "9", "Body": "9", "Flavor": "9", "Aftertaste": "9"}, {"Roaster Location": "Chia-Yi, Taiwan", "Coffee Origin": "Tore Village, Yirgacheffe growing region, southern Ethiopia", "Roast Level": "Medium-Light", "Agtron": "55/77", "Est. Price": "NT $550/16 ounces", "Review Date": "November 2017", "Aroma": "9", "Acidity /Structure ": "8", "Body": "9", "Flavor": "9", "Aftertaste": "8"}, {"Roaster Location": "Victoria, British Columbia, Canada", "Coffee Origin": "Africa; South America", "Roast Level": "Medium-Light", "Agtron": "51/73", "Est. Price": "CAD $17.00/16 ounces", "Review Date": "November 2017", "Aroma": "9", "Body": "8", "Flavor": "8", "Aftertaste": "8", "With Milk": "9"}, {"Roaster Location": "Sacramento, California", "Coffee Origin": "Sidama (also Sidamo) growing region, southern Ethiopia", "Roast Level": "Medium", "Agtron": "48/73", "Est. Price": "$19.50/12 ounces", "Review Date": "November 2017", "Aroma": "8", "Acidity /Structure ": "8", "Body": "7", "Flavor": "9", "Aftertaste": "8"}, {"Roaster Location": "Hong Kong, China", "Coffee Origin": "Not disclosed", "Roast Level": "Medium-Light", "Agtron": "55/74", "Est. Price": "HKD $128/227 grams", "Review Date": "November 2017", "Aroma": "8", "Body": "8", "Flavor": "9", "Aftertaste": "7", "With Milk": "8"}, {"Coffee Origin": "Not disclosed", "Roast Level": "Medium", "Agtron": "52/66", "Est. Price": "HKD $140/454 grams", "Review Date": "November 2017", "Aroma": "8", "Body": "8", "Flavor": "8", "Aftertaste": "8", "With Milk": "7"}, {"Roaster Location": "Hong Kong, China", "Coffee Origin": "Not disclosed", "Roast Level": "Medium-Light", "Agtron": "54/68", "Est. Price": "HKD $130/454 grams", "Review Date": "November 2017", "Aroma": "7", "Body": "8", "Flavor": "8", "Aftertaste": "7", "With Milk": "8"}, {"Roaster Location": "Hong Kong, China", "Coffee Origin": "Yirgacheffe growing region, southern Ethiopia", "Roast Level": "Medium-Light", "Agtron": "55/76", "Est. Price": "HKD $120/227 grams", "Review Date": "November 2017", "Aroma": "8", "Acidity /Structure ": "8", "Body": "9", "Flavor": "9", "Aftertaste": "8"}, {"Roaster Location": "Hong Kong, China", "Coffee Origin": "Not disclosed", "Roast Level": "Medium-Light", "Agtron": "50/74", "Est. Price": "HKD $128/454 grams", "Review Date": "November 2017", "Aroma": "9", "Acidity /Structure ": "8", "Body": "8", "Flavor": "9", "Aftertaste": "8"}, {"Roaster Location": "Hong Kong, China", "Coffee Origin": "Not disclosed", "Roast Level": "Medium-Light", "Agtron": "56/78", "Est. Price": "HKD $128/227 grams", "Review Date": "November 2017", "Aroma": "8", "Body": "9", "Flavor": "8", "Aftertaste": "7", "With Milk": "9"}, {"Roaster Location": "Hong Kong, China", "Coffee Origin": "Yirgacheffe growing region, southern Ethiopia", "Roast Level": "Medium-Light", "Agtron": "54/78", "Est. Price": "HKD $120/227 grams", "Review Date": "November 2017", "Aroma": "9", "Acidity /Structure ": "8", "Body": "8", "Flavor": "9", "Aftertaste": "7"}, {"Roaster Location": "Hong Kong, China", "Coffee Origin": "Ethiopia; Kenya; China", "Roast Level": "Medium-Light", "Agtron": "54/78", "Est. Price": "HKD $200/227 grams", "Review Date": "November 2017", "Aroma": "9", "Body": "9", "Flavor": "9", "Aftertaste": "9", "With Milk": "9"}, {"Roaster Location": "Hong Kong, China", "Coffee Origin": "Panama; Ethiopia", "Roast Level": "Medium-Light", "Agtron": "50/73", "Est. Price": "HKD $250/227 grams", "Review Date": "November 2017", "Aroma": "9", "Body": "9", "Flavor": "9", "Aftertaste": "9", "With Milk": "9"}, {"Roaster Location": "Hong Kong, China", "Coffee Origin": "Africa; Asia Pacific", "Roast Level": "Medium-Light", "Agtron": "54/77", "Est. Price": "HKD $158/227 grams", "Review Date": "November 2017", "Aroma": "9", "Body": "9", "Flavor": "9", "Aftertaste": "8", "With Milk": "9"}, {"Roaster Location": "Chino, California", "Coffee Origin": "Muranga County, south-central KenyaMur", "Roast Level": "Medium-Light", "Agtron": "52/70", "Est. Price": "$23.00/12 ounces", "Review Date": "October 2017", "Aroma": "9", "Acidity /Structure ": "8", "Body": "9", "Flavor": "9", "Aftertaste": "8"}, {"Roaster Location": "Daejeon, South Korea", "Coffee Origin": "Yirgacheffe growing region, southern Ethiopia", "Roast Level": "Medium-Light", "Agtron": "60/80", "Est. Price": "KRW $13,000/200 grams", "Review Date": "October 2017", "Aroma": "9", "Acidity /Structure ": "8", "Body": "9", "Flavor": "8", "Aftertaste": "8"}, {"Roaster Location": "Thermopolis, Wyoming", "Coffee Origin": "Boquete growing region, western Panama", "Roast Level": "Medium-Light", "Agtron": "52/74", "Est. Price": "$12.00/12 ounces", "Review Date": "October 2017", "Aroma": "8", "Acidity /Structure ": "8", "Body": "8", "Flavor": "9", "Aftertaste": "7"}, {"Roaster Location": "Madison, Wisconsin", "Coffee Origin": "Santa Ana region, El Salvador", "Roast Level": "Medium-Light", "Agtron": "54/75", "Est. Price": "$17.90/12 ounces", "Review Date": "October 2017", "Aroma": "9", "Body": "9", "Flavor": "9", "Aftertaste": "8", "With Milk": "9"}, {"Roaster Location": "Branford, Connecticut", "Coffee Origin": "Kiambu County, south-central Kenya", "Roast Level": "Medium-Light", "Agtron": "54/78", "Est. Price": "$19.99/16 ounces", "Review Date": "October 2017", "Aroma": "9", "Acidity /Structure ": "8", "Body": "9", "Flavor": "9", "Aftertaste": "8"}, {"Roaster Location": "San Diego, California", "Coffee Origin": "Huehuetenango Department, Guatemala", "Roast Level": "Medium-Light", "Agtron": "56/82", "Est. Price": "$51.00/8 ounces", "Review Date": "October 2017", "Aroma": "9", "Acidity /Structure ": "9", "Body": "8", "Flavor": "9", "Aftertaste": "9"}, {"Roaster Location": "Jakarta, Indonesia", "Coffee Origin": "Gayo (also Aceh) growing region, Aceh Province, northern Sumatra, Indonesia", "Roast Level": "Medium-Light", "Agtron": "54/76", "Est. Price": "IDR $120,000/250 grams", "Review Date": "October 2017", "Aroma": "9", "Acidity /Structure ": "8", "Body": "8", "Flavor": "9", "Aftertaste": "8"}, {"Roaster Location": "San Diego, California", "Coffee Origin": "El Salto, Boquete growing region, Panama", "Roast Level": "Medium-Light", "Agtron": "54/76", "Est. Price": "$18.00/8 ounces", "Review Date": "October 2017", "Aroma": "9", "Acidity /Structure ": "8", "Body": "9", "Flavor": "9", "Aftertaste": "8"}, {"Roaster Location": "San Diego, California", "Coffee Origin": "Sidama (also Sidamo) growing region, southern Ethiopia", "Roast Level": "Medium-Light", "Agtron": "52/74", "Est. Price": "$17.00/12 ounces", "Review Date": "October 2017", "Aroma": "9", "Body": "8", "Flavor": "8", "Aftertaste": "8", "With Milk": "9"}, {"Roaster Location": "I-Lan City, Taiwan", "Coffee Origin": "Nantou County, Taiwan", "Roast Level": "Medium-Light", "Agtron": "59/79", "Est. Price": "NT $1200/8 ounces", "Review Date": "October 2017", "Aroma": "9", "Acidity /Structure ": "8", "Body": "9", "Flavor": "9", "Aftertaste": "7"}, {"Roaster Location": "Boulder, Colorado", "Coffee Origin": "Nyeri growing region, south-central Kenya", "Roast Level": "Medium-Light", "Agtron": "56/76", "Est. Price": "$18.00/12 ounces", "Review Date": "October 2017", "Aroma": "9", "Acidity /Structure ": "9", "Body": "9", "Flavor": "9", "Aftertaste": "8"}, {"Roaster Location": "Floyd, Virginia", "Coffee Origin": "Colombia, Ethiopia, Kenya", "Roast Level": "Medium-Light", "Agtron": "56/80", "Est. Price": "$16.49/12 ounces", "Review Date": "October 2017", "Aroma": "9", "Body": "9", "Flavor": "9", "Aftertaste": "9", "With Milk": "9"}, {"Roaster Location": "Kaohsiung City, Taiwan", "Coffee Origin": "Panama; Ethiopia", "Roast Level": "Medium-Light", "Agtron": "56/76", "Est. Price": "$26.00/8 ounces", "Review Date": "October 2017", "Aroma": "9", "Body": "9", "Flavor": "9", "Aftertaste": "8", "With Milk": "10"}, {"Roaster Location": "Taipei City, Taiwan", "Coffee Origin": "Yirgacheffe growing region, southern Ethiopia", "Roast Level": "Medium-Light", "Agtron": "58/78", "Est. Price": "NT $1000/16 ounces", "Review Date": "October 2017", "Aroma": "8", "Acidity /Structure ": "9", "Body": "9", "Flavor": "9", "Aftertaste": "8"}, {"Roaster Location": "Bedford, New Hampshire", "Coffee Origin": "Yirgacheffe growing region, southern Ethiopia", "Roast Level": "Medium-Light", "Agtron": "52/74", "Est. Price": "$17.00/12 ounces", "Review Date": "October 2017", "Aroma": "9", "Acidity /Structure ": "8", "Body": "9", "Flavor": "9", "Aftertaste": "8"}, {"Roaster Location": "Palo Alto, California", "Coffee Origin": "Yirgacheffe growing region, southern Ethiopia", "Roast Level": "Medium-Light", "Agtron": "52/74", "Est. Price": "$12.99/8 ounces", "Review Date": "October 2017", "Aroma": "8", "Acidity /Structure ": "8", "Body": "9", "Flavor": "9", "Aftertaste": "8"}, {"Roaster Location": "Austin, Texas", "Coffee Origin": "Nyeri growing region, south-central Kenya", "Roast Level": "Medium-Light", "Agtron": "55/79", "Est. Price": "$18.00/12 ounces", "Review Date": "October 2017", "Aroma": "9", "Acidity /Structure ": "9", "Body": "8", "Flavor": "9", "Aftertaste": "9"}, {"Roaster Location": "Charlotte, North Carolina", "Coffee Origin": "Sabanilla de Alajuela growing region, Costa Rica", "Roast Level": "Medium-Light", "Agtron": "52/74", "Est. Price": "$14.99/12 ounces", "Review Date": "October 2017", "Aroma": "9", "Acidity /Structure ": "8", "Body": "8", "Flavor": "9", "Aftertaste": "8"}, {"Roaster Location": "Danville, Pennsylvania", "Coffee Origin": "Jinotega Department, north-central Nicaragua", "Roast Level": "Medium-Light", "Agtron": "57/79", "Est. Price": "$16.00/12 ounces", "Review Date": "October 2017", "Aroma": "9", "Acidity /Structure ": "8", "Body": "9", "Flavor": "9", "Aftertaste": "8"}, {"Roaster Location": "Chia-Yi, Taiwan", "Coffee Origin": "Matagalpa growing region, Nicaragua", "Roast Level": "Medium-Light", "Agtron": "56/75", "Est. Price": "NT $440/8 ounces", "Review Date": "October 2017", "Aroma": "9", "Acidity /Structure ": "8", "Body": "9", "Flavor": "9", "Aftertaste": "8"}, {"Roaster Location": "San Diego, California", "Coffee Origin": "Matagalpa growing region, Nicaragua", "Roast Level": "Light", "Agtron": "64/84", "Est. Price": "$16.00/12 ounces", "Review Date": "October 2017", "Aroma": "8", "Acidity /Structure ": "8", "Body": "9", "Flavor": "9", "Aftertaste": "9"}, {"Roaster Location": "Zhubei City, Taiwan", "Coffee Origin": "Nueva Segovia growing region, Nicaragua", "Roast Level": "Medium", "Agtron": "52/63", "Est. Price": "NT $950/16 ounces", "Review Date": "October 2017", "Aroma": "9", "Acidity /Structure ": "8", "Body": "9", "Flavor": "9", "Aftertaste": "8"}, {"Roaster Location": "Richmond, Virginia", "Coffee Origin": "Matagalpa growing region, Nicaragua", "Roast Level": "Light", "Agtron": "67/89", "Est. Price": "$18.99/8 ounces", "Review Date": "October 2017", "Aroma": "9", "Acidity /Structure ": "8", "Body": "8", "Flavor": "9", "Aftertaste": "8"}, {"Roaster Location": "Oakville, Ontario, Canada", "Coffee Origin": "Nueva Segovia growing region, Nicaragua", "Roast Level": "Medium-Light", "Agtron": "56/67", "Est. Price": "CAD $18.00/12 ounces", "Review Date": "October 2017", "Aroma": "9", "Acidity /Structure ": "8", "Body": "8", "Flavor": "9", "Aftertaste": "8"}, {"Roaster Location": "Fort Bragg, California", "Coffee Origin": "Matagalpa growing region, Nicaragua", "Roast Level": "Medium-Light", "Agtron": "58/77", "Est. Price": "$16.00/12 ounces", "Review Date": "October 2017", "Aroma": "8", "Acidity /Structure ": "8", "Body": "9", "Flavor": "9", "Aftertaste": "8"}, {"Roaster Location": "Torrington, Connecticut", "Coffee Origin": "Nueva Segovia growing region, Nicaragua", "Roast Level": "Medium-Light", "Agtron": "56/81", "Est. Price": "$16.99/12 ounces", "Review Date": "October 2017", "Aroma": "9", "Acidity /Structure ": "9", "Body": "9", "Flavor": "9", "Aftertaste": "8"}, {"Roaster Location": "Ramsey, Minnesota", "Coffee Origin": "Jinotega growing region, Nicaragua", "Roast Level": "Medium-Light", "Agtron": "53/78", "Est. Price": "$18.95/12 ounces", "Review Date": "October 2017", "Aroma": "9", "Acidity /Structure ": "9", "Body": "9", "Flavor": "9", "Aftertaste": "8"}, {"Roaster Location": "New Taipei City, Taiwan", "Coffee Origin": "Brazil; Colombia; Indonesia", "Roast Level": "Medium", "Agtron": "46/72", "Est. Price": "NT $450/454 grams", "Review Date": "October 2017", "Aroma": "8", "Body": "8", "Flavor": "8", "Aftertaste": "8", "With Milk": "9"}, {"Roaster Location": "Kaohslung City, Taiwan", "Coffee Origin": "Panama; Ethiopia", "Roast Level": "Light", "Agtron": "58/84", "Est. Price": "NT $300/8 ounces", "Review Date": "October 2017", "Aroma": "9", "Acidity /Structure ": "9", "Body": "8", "Flavor": "9", "Aftertaste": "8"}, {"Roaster Location": "Madison, Wisconsin", "Coffee Origin": "Gedeb District, Gedeo Zone, southern Ethiopia", "Roast Level": "Medium-Light", "Agtron": "58/82", "Est. Price": "$18.95/12 ounces", "Review Date": "September 2017", "Aroma": "9", "Acidity /Structure ": "9", "Body": "9", "Flavor": "9", "Aftertaste": "9"}, {"Roaster Location": "Madison, Wisconsin", "Coffee Origin": "Gedeb District, Gedeo Zone, southern Ethiopia", "Roast Level": "Medium-Light", "Agtron": "53/77", "Est. Price": "$17.90/12 ounces", "Review Date": "September 2017", "Aroma": "9", "Acidity /Structure ": "9", "Body": "8", "Flavor": "9", "Aftertaste": "9"}, {"Roaster Location": "Madison, Wisconsin", "Coffee Origin": "Kirinyaga District, south-central Kenya", "Roast Level": "Medium-Light", "Agtron": "56/78", "Est. Price": "$17.85/12 ounces", "Review Date": "September 2017", "Aroma": "9", "Acidity /Structure ": "8", "Body": "9", "Flavor": "9", "Aftertaste": "8"}, {"Roaster Location": "Madison, Wisconsin", "Coffee Origin": "Jacaltenango, Huehuetenango growing region, Guatemala", "Roast Level": "Medium-Light", "Agtron": "56/78", "Est. Price": "$15.75/12 ounces", "Review Date": "September 2017", "Aroma": "9", "Acidity /Structure ": "9", "Body": "8", "Flavor": "9", "Aftertaste": "8"}, {"Roaster Location": "Madison, Wisconsin", "Coffee Origin": "Santa Ana region, El Salvador", "Roast Level": "Medium-Light", "Agtron": "56/78", "Est. Price": "$17.90/12 ounces", "Review Date": "September 2017", "Aroma": "8", "Acidity /Structure ": "8", "Body": "9", "Flavor": "9", "Aftertaste": "8"}, {"Roaster Location": "Floyd, Virginia", "Coffee Origin": "Yirgacheffe growing region, southern Ethiopia", "Roast Level": "Medium-Light", "Agtron": "60/78", "Est. Price": "$16.49/12 ounces", "Review Date": "September 2017", "Aroma": "9", "Acidity /Structure ": "9", "Body": "9", "Flavor": "9", "Aftertaste": "8"}, {"Roaster Location": "Floyd, Virginia", "Coffee Origin": "Caldas Department, Colombia", "Roast Level": "Medium-Light", "Agtron": "54/70", "Est. Price": "$17.99/12 ounces", "Review Date": "September 2017", "Aroma": "9", "Acidity /Structure ": "8", "Body": "9", "Flavor": "9", "Aftertaste": "8"}, {"Roaster Location": "Chino, California", "Coffee Origin": "Yirgacheffe growing region, southern Ethiopia", "Roast Level": "Medium", "Agtron": "45/61", "Est. Price": "$17.00/12 ounces", "Review Date": "September 2017", "Aroma": "9", "Acidity /Structure ": "9", "Body": "9", "Flavor": "9", "Aftertaste": "9"}, {"Roaster Location": "Chino, California", "Coffee Origin": "Ethiopia; Colombia", "Roast Level": "Medium-Light", "Agtron": "54/68", "Est. Price": "$14.95/12 ounces", "Review Date": "September 2017", "Aroma": "9", "Body": "9", "Flavor": "9", "Aftertaste": "8", "With Milk": "9"}, {"Roaster Location": "Chino, California", "Coffee Origin": "Chiapas State, Mexico", "Roast Level": "Medium-Light", "Agtron": "51/73", "Est. Price": "$14.95/12 ounces", "Review Date": "September 2017", "Aroma": "9", "Body": "8", "Flavor": "9", "Aftertaste": "8", "With Milk": "9"}, {"Roaster Location": "Chino, California", "Coffee Origin": "Alajuela, Central Valley, Costa Rica", "Roast Level": "Medium-Light", "Agtron": "61/74", "Est. Price": "$16.00/12 ounces", "Review Date": "September 2017", "Aroma": "9", "Acidity /Structure ": "8", "Body": "9", "Flavor": "9", "Aftertaste": "8"}, {"Roaster Location": "Chino, California", "Coffee Origin": "Tarrazu growing region, Costa Rica", "Roast Level": "Medium", "Agtron": "52/69", "Est. Price": "$16.00/12 ounces", "Review Date": "September 2017", "Aroma": "9", "Acidity /Structure ": "8", "Body": "9", "Flavor": "9", "Aftertaste": "8"}, {"Roaster Location": "Chino, California", "Coffee Origin": "Huila Department, southern Colombia", "Roast Level": "Medium-Light", "Agtron": "55/77", "Est. Price": "$17.00/12 ounces", "Review Date": "September 2017", "Aroma": "8", "Acidity /Structure ": "8", "Body": "9", "Flavor": "9", "Aftertaste": "8"}, {"Roaster Location": "Chino, California", "Coffee Origin": "Yirgacheffe growing region, southern Ethiopia", "Roast Level": "Medium", "Agtron": "48/64", "Est. Price": "$17.00/12 ounces", "Review Date": "September 2017", "Aroma": "8", "Acidity /Structure ": "8", "Body": "8", "Flavor": "8", "Aftertaste": "8"}, {"Roaster Location": "Chino, California", "Coffee Origin": "Yirgacheffe growing region, southern Ethiopia", "Roast Level": "Medium", "Agtron": "51/69", "Est. Price": "$19.00/12 ounces", "Review Date": "September 2017", "Aroma": "8", "Acidity /Structure ": "8", "Body": "8", "Flavor": "9", "Aftertaste": "7"}, {"Roaster Location": "Chino, California", "Coffee Origin": "Antigua Valley, Guatemala", "Roast Level": "Medium", "Agtron": "50/56", "Est. Price": "$14.00/12 ounces", "Review Date": "September 2017", "Aroma": "8", "Acidity /Structure ": "8", "Body": "8", "Flavor": "9", "Aftertaste": "7"}, {"Roaster Location": "Chino, California", "Coffee Origin": "Cerrado growing region, Minas Gerais State, Brazil", "Roast Level": "Medium-Light", "Agtron": "53/74", "Est. Price": "$15.00/12 ounces", "Review Date": "September 2017", "Aroma": "8", "Acidity /Structure ": "8", "Body": "8", "Flavor": "8", "Aftertaste": "7"}, {"Roaster Location": "Chino, California", "Coffee Origin": "Chiapas State, Mexico", "Roast Level": "Medium-Light", "Agtron": "56/78", "Est. Price": "$14.00/12 ounces", "Review Date": "September 2017", "Aroma": "8", "Acidity /Structure ": "7", "Body": "8", "Flavor": "8", "Aftertaste": "7"}, {"Roaster Location": "Taipei, Taiwan", "Coffee Origin": "El Salvador", "Roast Level": "Light", "Agtron": "61/84", "Est. Price": "NT $490/225 grams", "Review Date": "September 2017", "Aroma": "9", "Acidity /Structure ": "9", "Body": "9", "Flavor": "9", "Aftertaste": "8"}, {"Roaster Location": "Chia-Yi, Taiwan", "Coffee Origin": "Kirinyaga District, south-central Kenya", "Roast Level": "Medium-Light", "Agtron": "59/77", "Est. Price": "NT $600/16 ounces", "Review Date": "September 2017", "Aroma": "9", "Acidity /Structure ": "9", "Body": "9", "Flavor": "9", "Aftertaste": "9"}, {"Roaster Location": "Chia-Yi, Taiwan", "Coffee Origin": "Acatenango growing region, central Guatemala", "Roast Level": "Medium-Light", "Agtron": "56/76", "Est. Price": "NT $550/16 ounces", "Review Date": "September 2017", "Aroma": "9", "Body": "9", "Flavor": "9", "Aftertaste": "8", "With Milk": "9"}, {"Roaster Location": "Chia-Yi, Taiwan", "Coffee Origin": "Yirgacheffe growing region, southern Ethiopia", "Roast Level": "Light", "Agtron": "60/82", "Est. Price": "NT $580/16 ounces", "Review Date": "September 2017", "Aroma": "9", "Acidity /Structure ": "8", "Body": "9", "Flavor": "9", "Aftertaste": "8"}, {"Roaster Location": "Winchester, Virginia", "Coffee Origin": "Nyeri growing region, south-central Kenya", "Roast Level": "Medium-Light", "Agtron": "59/78", "Est. Price": "$18.25/12 ounces", "Review Date": "September 2017", "Aroma": "8", "Acidity /Structure ": "8", "Body": "9", "Flavor": "9", "Aftertaste": "8"}, {"Roaster Location": "Crystal Lake, Illinois", "Coffee Origin": "Rwenzori Mountains, western Uganda", "Roast Level": "Medium-Light", "Agtron": "51/78", "Est. Price": "$19.75/16 ounces", "Review Date": "September 2017", "Aroma": "8", "Acidity /Structure ": "9", "Body": "9", "Flavor": "9", "Aftertaste": "8"}, {"Roaster Location": "Dubai, United Arab Emirates", "Coffee Origin": "LImmu Woreda, Oromia Zone, southern Ethiopia", "Roast Level": "Medium-Light", "Agtron": "58/78", "Est. Price": "AED $95.00/250 grams", "Review Date": "September 2017", "Aroma": "9", "Acidity /Structure ": "8", "Body": "9", "Flavor": "9", "Aftertaste": "8"}, {"Roaster Location": "Youngstown, Ohio", "Coffee Origin": "Marcala growing region, La Paz Department, Honduras", "Roast Level": "Medium-Light", "Agtron": "55/82", "Est. Price": "$14.00/10 ounces", "Review Date": "September 2017", "Aroma": "9", "Acidity /Structure ": "8", "Body": "9", "Flavor": "8", "Aftertaste": "7"}, {"Roaster Location": "Tulsa, Oklahoma", "Coffee Origin": "Guji Zone, southern Ethiopia", "Roast Level": "Medium-Light", "Agtron": "54/74", "Est. Price": "$15.99/12 ounces", "Review Date": "September 2017", "Aroma": "8", "Acidity /Structure ": "8", "Body": "8", "Flavor": "9", "Aftertaste": "7"}, {"Roaster Location": "Durango, Colorado", "Coffee Origin": "Pitalito, Huila Department, southern Colombia", "Roast Level": "Medium-Light", "Agtron": "55/77", "Est. Price": "$12.95/12 ounces", "Review Date": "September 2017", "Aroma": "9", "Acidity /Structure ": "9", "Body": "9", "Flavor": "9", "Aftertaste": "8"}, {"Roaster Location": "Tulsa, Oklahoma", "Coffee Origin": "Baringo and Nakura Counties, central Kenya", "Roast Level": "Medium-Light", "Agtron": "53/76", "Est. Price": "$15.99/12 ounces", "Review Date": "September 2017", "Aroma": "9", "Acidity /Structure ": "9", "Body": "9", "Flavor": "9", "Aftertaste": "8"}, {"Roaster Location": "Daejeon, South Korea", "Coffee Origin": "Guji Zone, southern Ethiopia", "Roast Level": "Light", "Agtron": "60/82", "Est. Price": "KRW $13,000/200 grams", "Review Date": "September 2017", "Aroma": "9", "Acidity /Structure ": "9", "Body": "9", "Flavor": "9", "Aftertaste": "8"}, {"Roaster Location": "Tulsa, Oklahoma", "Coffee Origin": "Baringo and Nakura Counties, central Kenya", "Roast Level": "Medium-Light", "Agtron": "54/76", "Est. Price": "$16.99/12 ounces", "Review Date": "September 2017", "Aroma": "9", "Acidity /Structure ": "9", "Body": "9", "Flavor": "9", "Aftertaste": "8"}, {"Roaster Location": "Markham, Ontario, Canada", "Coffee Origin": "Bench-Maji Zone, Southern Ethiopia", "Roast Level": "Medium-Light", "Agtron": "54/74", "Est. Price": "CAD $30.00/100 grams", "Review Date": "September 2017", "Aroma": "9", "Acidity /Structure ": "9", "Body": "9", "Flavor": "9", "Aftertaste": "9"}, {"Roaster Location": "Kaohslung City, Taiwan", "Coffee Origin": "Bench-Maji Zone, Southern Ethiopia", "Roast Level": "Light", "Agtron": "64/86", "Est. Price": "$37.00/4 ounces", "Review Date": "September 2017", "Aroma": "9", "Acidity /Structure ": "9", "Body": "9", "Flavor": "9", "Aftertaste": "9"}, {"Roaster Location": "Chia-Yi, Taiwan", "Coffee Origin": "Bench-Maji Zone, Southern Ethiopia", "Roast Level": "Medium-Light", "Agtron": "56/77", "Est. Price": "NT $3200/16 ounces", "Review Date": "September 2017", "Aroma": "9", "Acidity /Structure ": "9", "Body": "9", "Flavor": "10", "Aftertaste": "8"}, {"Roaster Location": "Charlottesville, Virginia", "Coffee Origin": "Bench-Maji Zone, Southern Ethiopia", "Roast Level": "Medium-Light", "Agtron": "54/78", "Est. Price": "$75.00/8 ounces", "Review Date": "September 2017", "Aroma": "10", "Acidity /Structure ": "9", "Body": "9", "Flavor": "9", "Aftertaste": "8"}, {"Roaster Location": "Boulder, Colorado", "Coffee Origin": "Boquete growing region, western Panama", "Roast Level": "Medium-Light", "Agtron": "54/78", "Est. Price": "$50.00/8 ounces", "Review Date": "September 2017", "Aroma": "9", "Acidity /Structure ": "9", "Body": "9", "Flavor": "9", "Aftertaste": "8"}, {"Roaster Location": "Lincoln, California", "Coffee Origin": "Boquete growing region, western Panama", "Roast Level": "Medium-Dark", "Agtron": "34/52", "Est. Price": "$29.99/12 ounces", "Review Date": "September 2017", "Aroma": "9", "Acidity /Structure ": "9", "Body": "8", "Flavor": "9", "Aftertaste": "9"}, {"Roaster Location": "Richmond, Virginia", "Coffee Origin": "Acatenango growing region, central Guatemala", "Roast Level": "Medium-Light", "Agtron": "57/78", "Est. Price": "$29.99/8 ounces", "Review Date": "September 2017", "Aroma": "9", "Acidity /Structure ": "9", "Body": "8", "Flavor": "9", "Aftertaste": "8"}, {"Roaster Location": "Yilan City, Taiwan", "Coffee Origin": "Bench-Maji Zone, Southern Ethiopia", "Roast Level": "Medium-Light", "Agtron": "53/74", "Est. Price": "NT $800/113.5 grams", "Review Date": "September 2017", "Aroma": "9", "Acidity /Structure ": "8", "Body": "9", "Flavor": "9", "Aftertaste": "8"}, {"Roaster Location": "Branford, Connecticut", "Coffee Origin": "Huehuetenango Department, Guatemala", "Roast Level": "Medium-Light", "Agtron": "52/76", "Est. Price": "$65.00/12 ounces", "Review Date": "September 2017", "Aroma": "8", "Acidity /Structure ": "8", "Body": "9", "Flavor": "9", "Aftertaste": "9"}, {"Roaster Location": "Boulder, Colorado", "Coffee Origin": "Boquete growing region, western Panama", "Roast Level": "Medium-Light", "Agtron": "54/78", "Est. Price": "$50.00/8 ounces", "Review Date": "September 2017", "Aroma": "9", "Acidity /Structure ": "10", "Body": "9", "Flavor": "9", "Aftertaste": "9"}, {"Roaster Location": "Portland, Oregon", "Coffee Origin": "Sidama (also Sidamo) growing region, southern Ethiopia", "Roast Level": "Medium-Light", "Agtron": "55/76", "Est. Price": "$15.00/250 grams", "Review Date": "August 2017", "Aroma": "9", "Acidity /Structure ": "8", "Body": "9", "Flavor": "9", "Aftertaste": "8"}, {"Roaster Location": "Billings, Montana", "Coffee Origin": "Mantiqeiras de Minas growing region, Minas Gerais State, Brazil", "Roast Level": "Medium-Light", "Agtron": "55/75", "Est. Price": "$15.00/12 ounces", "Review Date": "August 2017", "Aroma": "9", "Acidity /Structure ": "7", "Body": "8", "Flavor": "9", "Aftertaste": "8"}, {"Roaster Location": "Youngstown, Ohio", "Coffee Origin": "Huila Department, southern Colombia", "Roast Level": "Medium-Light", "Agtron": "53/77", "Est. Price": "$13.50/10 ounces", "Review Date": "August 2017", "Aroma": "8", "Acidity /Structure ": "9", "Body": "9", "Flavor": "9", "Aftertaste": "8"}, {"Roaster Location": "Youngstown, Ohio", "Coffee Origin": "Yirgacheffe growing region, southern Ethiopia", "Roast Level": "Medium-Light", "Agtron": "58/80", "Est. Price": "$13.50/10 ounces", "Review Date": "August 2017", "Aroma": "9", "Acidity /Structure ": "8", "Body": "9", "Flavor": "9", "Aftertaste": "8"}, {"Roaster Location": "Madison, Wisconsin", "Coffee Origin": "Antigua growing region, central Guatemala", "Roast Level": "Medium-Light", "Agtron": "56/78", "Est. Price": "$16.95/12 ounces", "Review Date": "August 2017", "Aroma": "9", "Acidity /Structure ": "8", "Body": "9", "Flavor": "9", "Aftertaste": "8"}, {"Roaster Location": "Ithaca, New York", "Coffee Origin": "Tarrazu growing region, Costa Rica", "Roast Level": "Medium-Light", "Agtron": "55/75", "Est. Price": "$14.99/12 ounces", "Review Date": "August 2017", "Aroma": "8", "Acidity /Structure ": "8", "Body": "8", "Flavor": "8", "Aftertaste": "8"}, {"Roaster Location": "Madison, Wisconsin", "Coffee Origin": "Nyeri growing region, south-central Kenya", "Roast Level": "Medium-Light", "Agtron": "53/77", "Est. Price": "$18.95/12 ounces", "Review Date": "August 2017", "Aroma": "9", "Body": "9", "Flavor": "9", "Aftertaste": "9", "With Milk": "9"}, {"Roaster Location": "Madison, Wisconsin", "Coffee Origin": "Yirgacheffe growing region, southern Ethiopia", "Roast Level": "Medium-Light", "Agtron": "51/73", "Est. Price": "$17.25/12 ounces", "Review Date": "August 2017", "Aroma": "9", "Body": "9", "Flavor": "9", "Aftertaste": "8", "With Milk": "9"}, {"Roaster Location": "Madison, Wisconsin", "Coffee Origin": "Yirgacheffe growing region, southern Ethiopia", "Roast Level": "Medium-Light", "Agtron": "55/77", "Est. Price": "$17.25/12 ounces", "Review Date": "August 2017", "Aroma": "9", "Acidity /Structure ": "8", "Body": "8", "Flavor": "9", "Aftertaste": "8"}, {"Roaster Location": "Madison, Wisconsin", "Coffee Origin": "Nyeri growing region, south-central Kenya", "Roast Level": "Medium-Light", "Agtron": "53/76", "Est. Price": "$18.95/12 ounces", "Review Date": "August 2017", "Aroma": "9", "Acidity /Structure ": "9", "Body": "9", "Flavor": "9", "Aftertaste": "9"}, {"Roaster Location": "Santa Rosa Beach, Florida", "Coffee Origin": "Narino Department, southern Colombia", "Roast Level": "Medium", "Agtron": "46/64", "Est. Price": "$29.95/6 ounces", "Review Date": "August 2017", "Aroma": "9", "Acidity /Structure ": "9", "Body": "9", "Flavor": "9", "Aftertaste": "9"}, {"Roaster Location": "Seoul, South Korea", "Coffee Origin": "Nyeri growing region, south-central Kenya", "Roast Level": "Medium-Dark", "Agtron": "41/49", "Est. Price": "KRW 19,000/200 grams", "Review Date": "August 2017", "Aroma": "9", "Acidity /Structure ": "9", "Body": "9", "Flavor": "9", "Aftertaste": "8"}, {"Roaster Location": "Missoula, Montana", "Coffee Origin": "Cajamarca growing region, Peru", "Roast Level": "Medium-Dark", "Agtron": "45/55", "Est. Price": "$15.50/12 ounces", "Review Date": "August 2017", "Aroma": "9", "Acidity /Structure ": "8", "Body": "9", "Flavor": "9", "Aftertaste": "8"}, {"Roaster Location": "Medford, Oregon", "Coffee Origin": "Southern Ethiopia", "Roast Level": "Dark", "Agtron": "32/38", "Est. Price": "$14.00/12 ounces", "Review Date": "August 2017", "Aroma": "9", "Acidity /Structure ": "8", "Body": "9", "Flavor": "9", "Aftertaste": "8"}, {"Roaster Location": "Montrose, Colorado", "Coffee Origin": "Mexico; Brazil", "Roast Level": "Medium-Dark", "Agtron": "46/52", "Est. Price": "$12.00/250 grams", "Review Date": "August 2017", "Aroma": "8", "Acidity /Structure ": "8", "Body": "9", "Flavor": "9", "Aftertaste": "8"}, {"Roaster Location": "Tequesta, Florida", "Coffee Origin": "Northern Sumatra, Indonesia", "Roast Level": "Medium-Dark", "Agtron": "39/49", "Est. Price": "$15.75/12 ounces", "Review Date": "August 2017", "Aroma": "9", "Acidity /Structure ": "8", "Body": "9", "Flavor": "9", "Aftertaste": "7"}, {"Roaster Location": "Ukiah, California", "Coffee Origin": "Not disclosed", "Roast Level": "Medium-Dark", "Agtron": "45/55", "Est. Price": "$14.00/12 ounces", "Review Date": "August 2017", "Aroma": "9", "Acidity ": "8", "Body": "8", "Flavor": "8", "Aftertaste": "8"}, {"Roaster Location": "San Rafael, California", "Coffee Origin": "Ethiopia; Sumatra, Indonesia", "Roast Level": "Medium-Dark", "Agtron": "44/56", "Est. Price": "$15.95/12 ounces", "Review Date": "August 2017", "Aroma": "8", "Acidity /Structure ": "8", "Body": "8", "Flavor": "9", "Aftertaste": "8"}, {"Roaster Location": "San Diego, California", "Coffee Origin": "Yirgacheffe growing region, Gedeo Zone, southern Ethiopia", "Roast Level": "Medium-Dark", "Agtron": "39/46", "Est. Price": "$24.00/12 ounces", "Review Date": "August 2017", "Aroma": "9", "Acidity /Structure ": "8", "Body": "8", "Flavor": "9", "Aftertaste": "7"}, {"Roaster Location": "Charlotte, North Carolina", "Coffee Origin": "Not disclosed", "Roast Level": "Medium-Dark", "Agtron": "45/55", "Est. Price": "$12.99/12 ounces", "Review Date": "August 2017", "Aroma": "9", "Acidity /Structure ": "8", "Body": "8", "Flavor": "8", "Aftertaste": "7"}, {"Roaster Location": "Columbus, Ohio", "Coffee Origin": "Yirgacheffe growing region, Gedeo Zone, southern Ethiopia", "Roast Level": "Medium-Dark", "Agtron": "45/52", "Est. Price": "$15.00/12 ounces", "Review Date": "August 2017", "Aroma": "8", "Acidity /Structure ": "8", "Body": "8", "Flavor": "8", "Aftertaste": "8"}, {"Roaster Location": "Fairfax, Virginia", "Coffee Origin": "Lintong growing region, northern Sumatra, Indonesia", "Roast Level": "Medium-Dark", "Agtron": "40/51", "Est. Price": "$12.00/10 ounces", "Review Date": "August 2017", "Aroma": "8", "Acidity /Structure ": "8", "Body": "8", "Flavor": "9", "Aftertaste": "7"}, {"Roaster Location": "Taipei, Taiwan", "Coffee Origin": "Kochere, Yirgacheffe growing region, south-central Ethiopia", "Roast Level": "Medium-Light", "Agtron": "58/82", "Est. Price": "NT $550/8 ounces", "Review Date": "August 2017", "Aroma": "9", "Acidity /Structure ": "9", "Body": "9", "Flavor": "10", "Aftertaste": "8"}, {"Roaster Location": "Ramsey, Minnesota", "Coffee Origin": "Lintong growing region, North Sumatra Province, Sumatra, Indonesia", "Roast Level": "Medium-Light", "Agtron": "55/77", "Est. Price": "$16.95/12 ounces", "Review Date": "August 2017", "Aroma": "9", "Acidity /Structure ": "8", "Body": "9", "Flavor": "9", "Aftertaste": "9"}, {"Roaster Location": "Lexington, Virginia", "Coffee Origin": "Bungoma region, western Kenya", "Roast Level": "Light", "Agtron": "60/84", "Est. Price": "$18.95/12 ounces", "Review Date": "August 2017", "Aroma": "9", "Acidity /Structure ": "9", "Body": "9", "Flavor": "9", "Aftertaste": "8"}, {"Roaster Location": "Santa Monica, California", "Coffee Origin": "Shakiso growing district, Guji Zone, Oromia Region, southern Ethiopia", "Roast Level": "Medium", "Agtron": "49/72", "Est. Price": "$20.00/12 ounces", "Review Date": "August 2017", "Aroma": "9", "Acidity /Structure ": "8", "Body": "9", "Flavor": "9", "Aftertaste": "8"}, {"Roaster Location": "Ramsey, Minnesota", "Coffee Origin": "Kalehe, South Kivu Province, Democratic Republic of the Congo", "Roast Level": "Medium-Light", "Agtron": "60/78", "Est. Price": "$16.95/12 ounces", "Review Date": "August 2017", "Aroma": "8", "Acidity /Structure ": "8", "Body": "9", "Flavor": "9", "Aftertaste": "8"}, {"Roaster Location": "Chia-Yi, Taiwan", "Coffee Origin": "Odo Shakiso District, Guji Zone, southern Ethiopia", "Roast Level": "Medium-Light", "Agtron": "58/80", "Est. Price": "NT $550/16 ounces", "Review Date": "August 2017", "Aroma": "9", "Acidity /Structure ": "9", "Body": "9", "Flavor": "9", "Aftertaste": "9"}, {"Roaster Location": "Crystal Lake, Illinois", "Coffee Origin": "Yirgacheffe growing region, southern Ethiopia", "Roast Level": "Medium-Light", "Agtron": "53/76", "Est. Price": "$22.00/16 ounces", "Review Date": "July 2017", "Aroma": "9", "Acidity /Structure ": "8", "Body": "8", "Flavor": "9", "Aftertaste": "8"}, {"Roaster Location": "Chino, California", "Coffee Origin": "Yirgacheffe growing region, southern Ethiopia", "Roast Level": "Medium", "Agtron": "48/73", "Est. Price": "$21.00/12 ounces", "Review Date": "July 2017", "Aroma": "8", "Acidity /Structure ": "8", "Body": "9", "Flavor": "9", "Aftertaste": "8"}, {"Roaster Location": "Madison, Wisconsin", "Coffee Origin": "Chiriqui Province, far western Panama", "Roast Level": "Light", "Agtron": "67/97", "Est. Price": "$68.50/4 ounces", "Review Date": "July 2017", "Aroma": "10", "Acidity ": "9", "Body": "9", "Flavor": "10", "Aftertaste": "9"}, {"Roaster Location": "Shanghai, China", "Coffee Origin": "Not disclosed", "Roast Level": "Medium", "Agtron": "46/64", "Est. Price": "RMB $60/8 ounces", "Review Date": "July 2017", "Aroma": "9", "Body": "8", "Flavor": "9", "Aftertaste": "8", "With Milk": "9"}, {"Roaster Location": "Lexington, Virginia", "Coffee Origin": "Yirgacheffe growing region, southern Ethiopia", "Roast Level": "Medium-Light", "Agtron": "51/74", "Est. Price": "$17.95/12 ounces", "Review Date": "July 2017", "Aroma": "9", "Acidity ": "8", "Body": "9", "Flavor": "8", "Aftertaste": "8"}, {"Roaster Location": "Madison, Wisconsin", "Coffee Origin": "Lintong growing region, North Sumatra Province, Sumatra, Indonesia", "Roast Level": "Medium-Light", "Agtron": "54/80", "Est. Price": "$16.50/12 ounces", "Review Date": "July 2017", "Aroma": "10", "Acidity ": "9", "Body": "9", "Flavor": "9", "Aftertaste": "8"}, {"Roaster Location": "Chicago, Illinois", "Coffee Origin": "Nyeri growing region, south-central Kenya", "Roast Level": "Light", "Agtron": "62/84", "Est. Price": "$14.00/12 ounces", "Review Date": "July 2017", "Aroma": "9", "Acidity ": "9", "Body": "9", "Flavor": "9", "Aftertaste": "8"}, {"Roaster Location": "Lexington, Virginia", "Coffee Origin": "Sabanilla de Alajuela growing region, Costa Rica", "Roast Level": "Medium-Light", "Agtron": "54/78", "Est. Price": "$18.95/12 ounces", "Review Date": "July 2017", "Aroma": "9", "Acidity ": "8", "Body": "9", "Flavor": "9", "Aftertaste": "8"}, {"Roaster Location": "Lexington, Virginia", "Coffee Origin": "Odo Shakiso District, Guji Zone, southern Ethiopia", "Roast Level": "Medium-Light", "Agtron": "53/78", "Est. Price": "$17.95/12 ounces", "Review Date": "July 2017", "Aroma": "9", "Acidity ": "8", "Body": "9", "Flavor": "9", "Aftertaste": "8"}, {"Roaster Location": "Nantou Hsien, Taiwan", "Coffee Origin": "Taiwan", "Roast Level": "Light", "Agtron": "74/93", "Est. Price": "NT $600/8 ounces", "Review Date": "July 2017", "Aroma": "8", "Acidity ": "8", "Body": "8", "Flavor": "8", "Aftertaste": "7"}, {"Roaster Location": "Tulsa, Oklahoma", "Coffee Origin": "Gaitania, Tolima Department, central Colombia", "Roast Level": "Medium-Light", "Agtron": "54/75", "Est. Price": "$15.99/12 ounces", "Review Date": "June 2017", "Aroma": "9", "Acidity ": "9", "Body": "9", "Flavor": "9", "Aftertaste": "8"}]